[
 {
  "Estado": "activa",
  "Fecha_inicio": "12\/08\/2023",
  "Fecha_fin": "12\/31\/2023",
  "SKU": 104069685,
  "para_quien": "Secret Santa",
  "edad": "Joven",
  "presupuesto": 50,
  "categoria": "Tecnologia",
  "Nombre": "AUDIFONO BT ON EAR JUNIOR 310 AZUL",
  "Descuento": "0.0%",
  "img": "https:\/\/siman.vtexassets.com\/arquivos\/ids\/3936515-1600-auto?v=638120876881730000&width=1600&height=auto&aspect=true",
  "url": "https:\/\/sv.siman.com\/audifonos-bt-junior-310-kids-azul-104069685\/p",
  "Precio_regular": 59,
  "Precio_promocion": 59,
  "Pais": "SV",
  "Inventario": 81
 },
 {
  "Estado": "activa",
  "Fecha_inicio": "12\/08\/2023",
  "Fecha_fin": "12\/31\/2023",
  "SKU": 104154291,
  "para_quien": "Secret Santa",
  "edad": "Joven",
  "presupuesto": 50,
  "categoria": "Tecnologia",
  "Nombre": "AUDIFONO BT ON EAR JUNIOR 310 ROJO",
  "Descuento": "0.0%",
  "img": "https:\/\/siman.vtexassets.com\/arquivos\/ids\/4205454-1600-auto?v=638186552675000000&width=1600&height=auto&aspect=true",
  "url": "https:\/\/sv.siman.com\/audifono-gaming-para-nios-104154291\/p",
  "Precio_regular": 59,
  "Precio_promocion": 59,
  "Pais": "SV",
  "Inventario": 14
 },
 {
  "Estado": "activa",
  "Fecha_inicio": "12\/08\/2023",
  "Fecha_fin": "12\/31\/2023",
  "SKU": 104069682,
  "para_quien": "Secret Santa",
  "edad": "Joven",
  "presupuesto": 50,
  "categoria": "Tecnologia",
  "Nombre": "AUDIFONO BT ON EAR JUNIOR 310 VERDE",
  "Descuento": "0.0%",
  "img": "https:\/\/siman.vtexassets.com\/arquivos\/ids\/3936501-1600-auto?v=638120876843200000&width=1600&height=auto&aspect=true",
  "url": "https:\/\/sv.siman.com\/audifonos-bt-junior-310-kids-green-104069682\/p",
  "Precio_regular": 59,
  "Precio_promocion": 59,
  "Pais": "SV",
  "Inventario": 89
 },
 {
  "Estado": "activa",
  "Fecha_inicio": "12\/08\/2023",
  "Fecha_fin": "12\/31\/2023",
  "SKU": 104084780,
  "para_quien": "Secret Santa",
  "edad": "Joven",
  "presupuesto": 100,
  "categoria": "Tecnologia",
  "Nombre": "AUDIFONO BT TRUE WIRELESS VIBE BEAM BEIGE",
  "Descuento": "0.0%",
  "img": "https:\/\/siman.vtexassets.com\/arquivos\/ids\/4016254-1600-auto?v=638138958556570000&width=1600&height=auto&aspect=true",
  "url": "https:\/\/sv.siman.com\/audifono-bt-true-wireless-vibe-beam-begam-104084780\/p",
  "Precio_regular": 64,
  "Precio_promocion": 64,
  "Pais": "SV",
  "Inventario": 40
 },
 {
  "Estado": "activa",
  "Fecha_inicio": "12\/08\/2023",
  "Fecha_fin": "12\/31\/2023",
  "SKU": 104084778,
  "para_quien": "Secret Santa",
  "edad": "Joven",
  "presupuesto": 100,
  "categoria": "Tecnologia",
  "Nombre": "AUDIFONO BT TRUE WIRELESS VIBE BEAM BLANCO",
  "Descuento": "0.0%",
  "img": "https:\/\/siman.vtexassets.com\/arquivos\/ids\/4016242-1600-auto?v=638138958526300000&width=1600&height=auto&aspect=true",
  "url": "https:\/\/sv.siman.com\/audifono-bt-true-wireless-vibe-beam-blanco-104084778\/p",
  "Precio_regular": 64,
  "Precio_promocion": 64,
  "Pais": "SV",
  "Inventario": 28
 },
 {
  "Estado": "activa",
  "Fecha_inicio": "12\/08\/2023",
  "Fecha_fin": "12\/31\/2023",
  "SKU": 104084779,
  "para_quien": "Secret Santa",
  "edad": "Joven",
  "presupuesto": 100,
  "categoria": "Tecnologia",
  "Nombre": "AUDIFONO BT TRUE WIRELESS VIBE BEAM MENTA",
  "Descuento": "0.0%",
  "img": "https:\/\/siman.vtexassets.com\/arquivos\/ids\/4016248-1600-auto?v=638138958542800000&width=1600&height=auto&aspect=true",
  "url": "https:\/\/sv.siman.com\/audifono-bt-true-wireless-vibe-beam-menta-104084779\/p",
  "Precio_regular": 64,
  "Precio_promocion": 64,
  "Pais": "SV",
  "Inventario": 34
 },
 {
  "Estado": "activa",
  "Fecha_inicio": "12\/08\/2023",
  "Fecha_fin": "12\/31\/2023",
  "SKU": 104269684,
  "para_quien": "Secret Santa",
  "edad": "Joven",
  "presupuesto": 50,
  "categoria": "Tecnologia",
  "Nombre": "AUDIFONO BT TRUE WIRELESS VIBE BUDS BEIGE",
  "Descuento": "0.0%",
  "img": "https:\/\/siman.vtexassets.com\/arquivos\/ids\/4574256-1600-auto?v=638279098433200000&width=1600&height=auto&aspect=true",
  "url": "https:\/\/sv.siman.com\/audifono-bt-true-wireless-vibe-buds-beige-104269684\/p",
  "Precio_regular": 54,
  "Precio_promocion": 54,
  "Pais": "SV",
  "Inventario": 26
 },
 {
  "Estado": "activa",
  "Fecha_inicio": "12\/08\/2023",
  "Fecha_fin": "12\/31\/2023",
  "SKU": 104084775,
  "para_quien": "Secret Santa",
  "edad": "Joven",
  "presupuesto": 50,
  "categoria": "Tecnologia",
  "Nombre": "AUDIFONO BT TRUE WIRELESS VIBE BUDS BLANCOS",
  "Descuento": "0.0%",
  "img": "https:\/\/siman.vtexassets.com\/arquivos\/ids\/4016224-1600-auto?v=638138958480830000&width=1600&height=auto&aspect=true",
  "url": "https:\/\/sv.siman.com\/audifono-bt-true-wireless-vibe-buds-blancos-104084775\/p",
  "Precio_regular": 54,
  "Precio_promocion": 54,
  "Pais": "SV",
  "Inventario": 18
 },
 {
  "Estado": "activa",
  "Fecha_inicio": "12\/08\/2023",
  "Fecha_fin": "12\/31\/2023",
  "SKU": 104084776,
  "para_quien": "Secret Santa",
  "edad": "Joven",
  "presupuesto": 50,
  "categoria": "Tecnologia",
  "Nombre": "AUDIFONO BT TRUE WIRELESS VIBE BUDS MENTA",
  "Descuento": "0.0%",
  "img": "https:\/\/siman.vtexassets.com\/arquivos\/ids\/4016231-1600-auto?v=638138958497100000&width=1600&height=auto&aspect=true",
  "url": "https:\/\/sv.siman.com\/audifono-bt-true-wireless-vibe-buds-menta-104084776\/p",
  "Precio_regular": 54,
  "Precio_promocion": 54,
  "Pais": "SV",
  "Inventario": 25
 },
 {
  "Estado": "activa",
  "Fecha_inicio": "12\/08\/2023",
  "Fecha_fin": "12\/31\/2023",
  "SKU": 104087647,
  "para_quien": "Secret Santa",
  "edad": "Joven",
  "presupuesto": 50,
  "categoria": "Tecnologia",
  "Nombre": "AUDIFONO BT TRUE WIRELESS VIBE BUDS NEGROS",
  "Descuento": "0.0%",
  "img": "https:\/\/siman.vtexassets.com\/arquivos\/ids\/4016270-1600-auto?v=638138958593400000&width=1600&height=auto&aspect=true",
  "url": "https:\/\/sv.siman.com\/audifono-bt-true-wireless-vibe-buds-negros-104087647\/p",
  "Precio_regular": 54,
  "Precio_promocion": 54,
  "Pais": "SV",
  "Inventario": 178
 },
 {
  "Estado": "activa",
  "Fecha_inicio": "12\/08\/2023",
  "Fecha_fin": "12\/31\/2023",
  "SKU": 104084781,
  "para_quien": "Secret Santa",
  "edad": "Joven",
  "presupuesto": 25,
  "categoria": "Tecnologia",
  "Nombre": "AUDIFONO IN EAR BT ENDURANCE RUN AMARILLO\/GRIS",
  "Descuento": "0.0%",
  "img": "https:\/\/siman.vtexassets.com\/arquivos\/ids\/4016263-1600-auto?v=638138958576870000&width=1600&height=auto&aspect=true",
  "url": "https:\/\/sv.siman.com\/audifono-in-ear-bt-endurance-run-amarillo-gris-104084781\/p",
  "Precio_regular": 25.9,
  "Precio_promocion": 25.9,
  "Pais": "SV",
  "Inventario": 184
 },
 {
  "Estado": "activa",
  "Fecha_inicio": "12\/08\/2023",
  "Fecha_fin": "12\/31\/2023",
  "SKU": 104362367,
  "para_quien": "Secret Santa",
  "edad": "Joven",
  "presupuesto": 25,
  "categoria": "Tecnologia",
  "Nombre": "AUDIFONO IN EAR BT ENDURANCE RUN AZUL",
  "Descuento": "0.0%",
  "img": "https:\/\/siman.vtexassets.com\/arquivos\/ids\/4763104-1600-auto?v=638321113680270000&width=1600&height=auto&aspect=true",
  "url": "https:\/\/sv.siman.com\/audifono-in-ear-bt-endurance-run-azul-104362367\/p",
  "Precio_regular": 25.9,
  "Precio_promocion": 25.9,
  "Pais": "SV",
  "Inventario": 226
 },
 {
  "Estado": "activa",
  "Fecha_inicio": "12\/08\/2023",
  "Fecha_fin": "12\/31\/2023",
  "SKU": 104206612,
  "para_quien": "Secret Santa",
  "edad": "Joven",
  "presupuesto": 25,
  "categoria": "Tecnologia",
  "Nombre": "AUDIFONO IN EAR REDMI BUDS 4 LITE BLANCO",
  "Descuento": "0.0%",
  "img": "https:\/\/siman.vtexassets.com\/arquivos\/ids\/4410666-1600-auto?v=638237402493730000&width=1600&height=auto&aspect=true",
  "url": "https:\/\/sv.siman.com\/audifono-in-ear-redmi-buds-4-lite-blanco-104206612\/p",
  "Precio_regular": 29,
  "Precio_promocion": 29,
  "Pais": "SV",
  "Inventario": 509
 },
 {
  "Estado": "activa",
  "Fecha_inicio": "12\/08\/2023",
  "Fecha_fin": "12\/31\/2023",
  "SKU": 104206611,
  "para_quien": "Secret Santa",
  "edad": "Joven",
  "presupuesto": 25,
  "categoria": "Tecnologia",
  "Nombre": "AUDIFONO IN EAR REDMI BUDS 4 LITE NEGRO",
  "Descuento": "0.0%",
  "img": "https:\/\/siman.vtexassets.com\/arquivos\/ids\/4410661-1600-auto?v=638237402477430000&width=1600&height=auto&aspect=true",
  "url": "https:\/\/sv.siman.com\/audifono-in-ear-redmi-buds-4-lite-negro-104206611\/p",
  "Precio_regular": 29,
  "Precio_promocion": 29,
  "Pais": "SV",
  "Inventario": 905
 },
 {
  "Estado": "activa",
  "Fecha_inicio": "12\/08\/2023",
  "Fecha_fin": "12\/31\/2023",
  "SKU": 104094139,
  "para_quien": "Secret Santa",
  "edad": "Joven",
  "presupuesto": 100,
  "categoria": "Tecnologia",
  "Nombre": "AUDIFONO IN EAR TWS REDMI BUDS 4 PRO BLANCOS",
  "Descuento": "30.3%",
  "img": "https:\/\/siman.vtexassets.com\/arquivos\/ids\/4014550-1600-auto?v=638138288437070000&width=1600&height=auto&aspect=true",
  "url": "https:\/\/sv.siman.com\/audifono-in-ear-tws-redmi-buds-4-pro-blancos-104094139\/p",
  "Precio_regular": 99,
  "Precio_promocion": 69,
  "Pais": "SV",
  "Inventario": 88
 },
 {
  "Estado": "activa",
  "Fecha_inicio": "12\/08\/2023",
  "Fecha_fin": "12\/31\/2023",
  "SKU": 104094138,
  "para_quien": "Secret Santa",
  "edad": "Joven",
  "presupuesto": 100,
  "categoria": "Tecnologia",
  "Nombre": "AUDIFONO IN EAR TWS REDMI BUDS 4 PRO NEGROS",
  "Descuento": "30.3%",
  "img": "https:\/\/siman.vtexassets.com\/arquivos\/ids\/4014545-1600-auto?v=638138288424400000&width=1600&height=auto&aspect=true",
  "url": "https:\/\/sv.siman.com\/audifono-in-ear-tws-redmi-buds-4-pro-negros-104094138\/p",
  "Precio_regular": 99,
  "Precio_promocion": 69,
  "Pais": "SV",
  "Inventario": 51
 },
 {
  "Estado": "activa",
  "Fecha_inicio": "12\/08\/2023",
  "Fecha_fin": "12\/31\/2023",
  "SKU": 101201415,
  "para_quien": "Secret Santa",
  "edad": "Joven",
  "presupuesto": 25,
  "categoria": "Tecnologia",
  "Nombre": "AUDIFONOS CON MICROFONO INTRAURALES T110 AZULES",
  "Descuento": "0.0%",
  "img": "https:\/\/siman.vtexassets.com\/arquivos\/ids\/325421-1600-auto?v=637250606445430000&width=1600&height=auto&aspect=true",
  "url": "https:\/\/sv.siman.com\/audifono-jbl-tune-110-azules-101201415\/p",
  "Precio_regular": 14.9,
  "Precio_promocion": 14.9,
  "Pais": "SV",
  "Inventario": 249
 },
 {
  "Estado": "activa",
  "Fecha_inicio": "12\/08\/2023",
  "Fecha_fin": "12\/31\/2023",
  "SKU": 101201413,
  "para_quien": "Secret Santa",
  "edad": "Joven",
  "presupuesto": 25,
  "categoria": "Tecnologia",
  "Nombre": "AUDIFONOS CON MICROFONO INTRAURALES T110 BLANCOS",
  "Descuento": "0.0%",
  "img": "https:\/\/siman.vtexassets.com\/arquivos\/ids\/325420-1600-auto?v=637250606440600000&width=1600&height=auto&aspect=true",
  "url": "https:\/\/sv.siman.com\/audifono-jbl-tune-110-blancos-101201413\/p",
  "Precio_regular": 14.9,
  "Precio_promocion": 14.9,
  "Pais": "SV",
  "Inventario": 229
 },
 {
  "Estado": "activa",
  "Fecha_inicio": "12\/08\/2023",
  "Fecha_fin": "12\/31\/2023",
  "SKU": 100783980,
  "para_quien": "Secret Santa",
  "edad": "Joven",
  "presupuesto": 25,
  "categoria": "Tecnologia",
  "Nombre": "AUDIFONOS CON MICROFONO INTRAURALES T110 NEGRO",
  "Descuento": "0.0%",
  "img": "https:\/\/siman.vtexassets.com\/arquivos\/ids\/3865688-1600-auto?v=638101760048430000&width=1600&height=auto&aspect=true",
  "url": "https:\/\/sv.siman.com\/audifono-in-ear-con-microfono-y-cable-flat-negros-100783980\/p",
  "Precio_regular": 14.9,
  "Precio_promocion": 14.9,
  "Pais": "SV",
  "Inventario": 375
 },
 {
  "Estado": "activa",
  "Fecha_inicio": "12\/08\/2023",
  "Fecha_fin": "12\/31\/2023",
  "SKU": 104154277,
  "para_quien": "Secret Santa",
  "edad": "Joven",
  "presupuesto": 100,
  "categoria": "Tecnologia",
  "Nombre": "AUDIFONOS ON EAR BT CON MICRONOFO AZUL",
  "Descuento": "28.3%",
  "img": "https:\/\/siman.vtexassets.com\/arquivos\/ids\/4205378-1600-auto?v=638186552498400000&width=1600&height=auto&aspect=true",
  "url": "https:\/\/sv.siman.com\/audifono-de-diadema-wh-ch520-inalambrico-bt-azul-104154277\/p",
  "Precio_regular": 64,
  "Precio_promocion": 45.9,
  "Pais": "SV",
  "Inventario": 320
 },
 {
  "Estado": "activa",
  "Fecha_inicio": "12\/08\/2023",
  "Fecha_fin": "12\/31\/2023",
  "SKU": 104154278,
  "para_quien": "Secret Santa",
  "edad": "Joven",
  "presupuesto": 100,
  "categoria": "Tecnologia",
  "Nombre": "AUDIFONOS ON EAR BT CON MICRONOFO BEIGE",
  "Descuento": "28.3%",
  "img": "https:\/\/siman.vtexassets.com\/arquivos\/ids\/4205386-1600-auto?v=638186552514870000&width=1600&height=auto&aspect=true",
  "url": "https:\/\/sv.siman.com\/audifono-de-diadema-wh-ch520-inalambrico-bt-beige-104154278\/p",
  "Precio_regular": 64,
  "Precio_promocion": 45.9,
  "Pais": "SV",
  "Inventario": 30
 },
 {
  "Estado": "activa",
  "Fecha_inicio": "12\/08\/2023",
  "Fecha_fin": "12\/31\/2023",
  "SKU": 103670922,
  "para_quien": "Secret Santa",
  "edad": "Joven",
  "presupuesto": "100+",
  "categoria": "Tecnologia",
  "Nombre": "BOCINA INALAMBRICA FLIP6 ESTEREO NEGRA",
  "Descuento": "20.1%",
  "img": "https:\/\/siman.vtexassets.com\/arquivos\/ids\/2758617-1600-auto?v=637843653236770000&width=1600&height=auto&aspect=true",
  "url": "https:\/\/sv.siman.com\/bocina-inalambrica-flip6-estereo-negra-103670922\/p",
  "Precio_regular": 149,
  "Precio_promocion": 119,
  "Pais": "SV",
  "Inventario": 22
 },
 {
  "Estado": "activa",
  "Fecha_inicio": "12\/08\/2023",
  "Fecha_fin": "12\/31\/2023",
  "SKU": 103913429,
  "para_quien": "Secret Santa",
  "edad": "Joven",
  "presupuesto": "100+",
  "categoria": "Tecnologia",
  "Nombre": "BOCINA INALAMBRICA FLIP6 ESTEREO ROSA",
  "Descuento": "20.1%",
  "img": "https:\/\/siman.vtexassets.com\/arquivos\/ids\/3421447-1600-auto?v=637999831576400000&width=1600&height=auto&aspect=true",
  "url": "https:\/\/sv.siman.com\/jbl-speaker-bt-flip-6-pink-103913429\/p",
  "Precio_regular": 149,
  "Precio_promocion": 119,
  "Pais": "SV",
  "Inventario": 24
 },
 {
  "Estado": "activa",
  "Fecha_inicio": "12\/08\/2023",
  "Fecha_fin": "12\/31\/2023",
  "SKU": 104062501,
  "para_quien": "Secret Santa",
  "edad": "Joven",
  "presupuesto": "100+",
  "categoria": "Tecnologia",
  "Nombre": "BOCINA INALAMBRICA FLIP6 ESTEREO VERDE",
  "Descuento": "20.1%",
  "img": "https:\/\/siman.vtexassets.com\/arquivos\/ids\/3935145-1600-auto?v=638120634689270000&width=1600&height=auto&aspect=true",
  "url": "https:\/\/sv.siman.com\/bocina-inalambrica-flip6-estereo-verde-104062501\/p",
  "Precio_regular": 149,
  "Precio_promocion": 119,
  "Pais": "SV",
  "Inventario": 90
 },
 {
  "Estado": "activa",
  "Fecha_inicio": "12\/08\/2023",
  "Fecha_fin": "12\/31\/2023",
  "SKU": 104372962,
  "para_quien": "Secret Santa",
  "edad": "Joven",
  "presupuesto": 50,
  "categoria": "Tecnologia",
  "Nombre": "BOCINA SMART AMAZON ECHO AUTO INALÁMBRICA NEGRA",
  "Descuento": "0.0%",
  "img": "https:\/\/siman.vtexassets.com\/arquivos\/ids\/4789428-1600-auto?v=638326565858070000&width=1600&height=auto&aspect=true",
  "url": "https:\/\/sv.siman.com\/bocina-smart-amazon-echo-auto-inalambrica-negra-104372962\/p",
  "Precio_regular": 39,
  "Precio_promocion": 39,
  "Pais": "SV",
  "Inventario": 14
 },
 {
  "Estado": "activa",
  "Fecha_inicio": "12\/08\/2023",
  "Fecha_fin": "12\/31\/2023",
  "SKU": 104265789,
  "para_quien": "Secret Santa",
  "edad": "Joven",
  "presupuesto": 100,
  "categoria": "Tecnologia",
  "Nombre": "BOCINA SMART AMAZON ECHO DOT 5TA GEN KID BÚHO",
  "Descuento": "17.3%",
  "img": "https:\/\/siman.vtexassets.com\/arquivos\/ids\/4596555-1600-auto?v=638284228091470000&width=1600&height=auto&aspect=true",
  "url": "https:\/\/sv.siman.com\/bocina-smart-amazon-echo-dot-5ta-gen-kid-buho-104265789\/p",
  "Precio_regular": 75,
  "Precio_promocion": 62,
  "Pais": "SV",
  "Inventario": 17
 },
 {
  "Estado": "activa",
  "Fecha_inicio": "12\/08\/2023",
  "Fecha_fin": "12\/31\/2023",
  "SKU": 104265790,
  "para_quien": "Secret Santa",
  "edad": "Joven",
  "presupuesto": 100,
  "categoria": "Tecnologia",
  "Nombre": "BOCINA SMART AMAZON ECHO DOT 5TA GEN KID DRAGÓN",
  "Descuento": "17.3%",
  "img": "https:\/\/siman.vtexassets.com\/arquivos\/ids\/4596559-1600-auto?v=638284228130270000&width=1600&height=auto&aspect=true",
  "url": "https:\/\/sv.siman.com\/bocina-smart-amazon-echo-dot-5ta-gen-kid-dragon-104265790\/p",
  "Precio_regular": 75,
  "Precio_promocion": 62,
  "Pais": "SV",
  "Inventario": 20
 },
 {
  "Estado": "activa",
  "Fecha_inicio": "12\/08\/2023",
  "Fecha_fin": "12\/31\/2023",
  "SKU": 104045122,
  "para_quien": "Secret Santa",
  "edad": "Joven",
  "presupuesto": 100,
  "categoria": "Tecnologia",
  "Nombre": "BOCINA SMART AMAZON ECHO DOT AZUL 5TA GEN",
  "Descuento": "19.0%",
  "img": "https:\/\/siman.vtexassets.com\/arquivos\/ids\/3936412-1600-auto?v=638120876591770000&width=1600&height=auto&aspect=true",
  "url": "https:\/\/sv.siman.com\/bocina-smart-amazon-echo-dot-azul-4ta-gen-104045122\/p",
  "Precio_regular": 79,
  "Precio_promocion": 64,
  "Pais": "SV",
  "Inventario": 83
 },
 {
  "Estado": "activa",
  "Fecha_inicio": "12\/08\/2023",
  "Fecha_fin": "12\/31\/2023",
  "SKU": 104045120,
  "para_quien": "Secret Santa",
  "edad": "Joven",
  "presupuesto": 100,
  "categoria": "Tecnologia",
  "Nombre": "BOCINA SMART AMAZON ECHO DOT NEGRA 5TA GEN",
  "Descuento": "19.0%",
  "img": "https:\/\/siman.vtexassets.com\/arquivos\/ids\/3936405-1600-auto?v=638120876569730000&width=1600&height=auto&aspect=true",
  "url": "https:\/\/sv.siman.com\/bocina-smart-amazon-echo-dot-negra-5ta-gen-104045120\/p",
  "Precio_regular": 79,
  "Precio_promocion": 64,
  "Pais": "SV",
  "Inventario": 119
 },
 {
  "Estado": "activa",
  "Fecha_inicio": "12\/08\/2023",
  "Fecha_fin": "12\/31\/2023",
  "SKU": 103844798,
  "para_quien": "Secret Santa",
  "edad": "Joven",
  "presupuesto": "100+",
  "categoria": "Tecnologia",
  "Nombre": "JBL CHARGE 5 PARLANTE COLOR AQUA",
  "Descuento": "21.2%",
  "img": "https:\/\/siman.vtexassets.com\/arquivos\/ids\/3245686-1600-auto?v=637964335318100000&width=1600&height=auto&aspect=true",
  "url": "https:\/\/sv.siman.com\/bocina-bt-charge-5-103844798\/p",
  "Precio_regular": 189,
  "Precio_promocion": 149,
  "Pais": "SV",
  "Inventario": 30
 },
 {
  "Estado": "activa",
  "Fecha_inicio": "12\/08\/2023",
  "Fecha_fin": "12\/31\/2023",
  "SKU": 103351228,
  "para_quien": "Secret Santa",
  "edad": "Joven",
  "presupuesto": "100+",
  "categoria": "Tecnologia",
  "Nombre": "JBL CHARGE 5 PARLANTE COLOR AZUL",
  "Descuento": "21.2%",
  "img": "https:\/\/siman.vtexassets.com\/arquivos\/ids\/1495991-1600-auto?v=637598890198870000&width=1600&height=auto&aspect=true",
  "url": "https:\/\/sv.siman.com\/jbl-charge-5-parlante-color-azul-103351228\/p",
  "Precio_regular": 189,
  "Precio_promocion": 149,
  "Pais": "SV",
  "Inventario": 43
 },
 {
  "Estado": "activa",
  "Fecha_inicio": "12\/08\/2023",
  "Fecha_fin": "12\/31\/2023",
  "SKU": 104050128,
  "para_quien": "Secret Santa",
  "edad": "Joven",
  "presupuesto": "100+",
  "categoria": "Tecnologia",
  "Nombre": "JBL CHARGE 5 PARLANTE COLOR GRIS",
  "Descuento": "21.2%",
  "img": "https:\/\/siman.vtexassets.com\/arquivos\/ids\/3892344-1600-auto?v=638108790870270000&width=1600&height=auto&aspect=true",
  "url": "https:\/\/sv.siman.com\/bocina-portatil-charge-5-gris-104050128\/p",
  "Precio_regular": 189,
  "Precio_promocion": 149,
  "Pais": "SV",
  "Inventario": 53
 },
 {
  "Estado": "activa",
  "Fecha_inicio": "12\/08\/2023",
  "Fecha_fin": "12\/31\/2023",
  "SKU": 104218095,
  "para_quien": "Secret Santa",
  "edad": "Joven",
  "presupuesto": 100,
  "categoria": "Tecnologia",
  "Nombre": "REPRODUCTOR MULTIMEDIA CHROMECAST CON GOOGLE TV HD",
  "Descuento": "0.0%",
  "img": "https:\/\/siman.vtexassets.com\/arquivos\/ids\/4411055-1600-auto?v=638237403857600000&width=1600&height=auto&aspect=true",
  "url": "https:\/\/sv.siman.com\/reproductor-multimedia-chromecast-con-google-tv-hd-104218095\/p",
  "Precio_regular": 59,
  "Precio_promocion": 59,
  "Pais": "SV",
  "Inventario": 67
 },
 {
  "Estado": "activa",
  "Fecha_inicio": "12\/08\/2023",
  "Fecha_fin": "12\/31\/2023",
  "SKU": 103631672,
  "para_quien": "Secret Santa",
  "edad": "Joven",
  "presupuesto": 100,
  "categoria": "Tecnologia",
  "Nombre": "REPRODUCTOR MULTIMEDIA FIRE TV STICK HD 3RA. GEN. ALEXA",
  "Descuento": "23.2%",
  "img": "https:\/\/siman.vtexassets.com\/arquivos\/ids\/2638304-1600-auto?v=637810725118930000&width=1600&height=auto&aspect=true",
  "url": "https:\/\/sv.siman.com\/reproductor-multimedia-fire-tv-stick-hd-3ra-gen-alexa-103631672\/p",
  "Precio_regular": 65,
  "Precio_promocion": 49.9,
  "Pais": "SV",
  "Inventario": 209
 },
 {
  "Estado": "activa",
  "Fecha_inicio": "12\/08\/2023",
  "Fecha_fin": "12\/31\/2023",
  "SKU": 103631673,
  "para_quien": "Secret Santa",
  "edad": "Joven",
  "presupuesto": 100,
  "categoria": "Tecnologia",
  "Nombre": "REPRODUCTOR MULTIMEDIA FIRE TV STICK UHD 4K ALEXA",
  "Descuento": "0.0%",
  "img": "https:\/\/siman.vtexassets.com\/arquivos\/ids\/2638307-1600-auto?v=637810725126270000&width=1600&height=auto&aspect=true",
  "url": "https:\/\/sv.siman.com\/reproductor-multimedia-fire-tv-stick-uhd-4k-alexa-103631673\/p",
  "Precio_regular": 69,
  "Precio_promocion": 69,
  "Pais": "SV",
  "Inventario": 47
 },
 {
  "Estado": "activa",
  "Fecha_inicio": "12\/08\/2023",
  "Fecha_fin": "12\/31\/2023",
  "SKU": 104372964,
  "para_quien": "Secret Santa",
  "edad": "Joven",
  "presupuesto": 100,
  "categoria": "Tecnologia",
  "Nombre": "REPRODUCTOR MULTIMEDIA FIRE TV STICK UHD 4K MAX ALEXA",
  "Descuento": "0.0%",
  "img": "https:\/\/siman.vtexassets.com\/arquivos\/ids\/4789436-1600-auto?v=638326565883370000&width=1600&height=auto&aspect=true",
  "url": "https:\/\/sv.siman.com\/reproductor-multimedia-fire-tv-stick-uhd-4k-max-alexa-104372964\/p",
  "Precio_regular": 69,
  "Precio_promocion": 69,
  "Pais": "SV",
  "Inventario": 107
 },
 {
  "Estado": "activa",
  "Fecha_inicio": "12\/08\/2023",
  "Fecha_fin": "12\/31\/2023",
  "SKU": 104215432,
  "para_quien": "Secret Santa",
  "edad": "Joven",
  "presupuesto": 100,
  "categoria": "Tecnologia",
  "Nombre": "REPRODUCTOR MULTIMEDIA MI TV STICK 4K",
  "Descuento": "14.5%",
  "img": "https:\/\/siman.vtexassets.com\/arquivos\/ids\/4410858-800-auto?v=638237403148700000&width=800&height=auto&aspect=true",
  "url": "https:\/\/sv.siman.com\/reproductor-multimedia-mi-tv-stick-4k-104215432\/p",
  "Precio_regular": 69,
  "Precio_promocion": 59,
  "Pais": "SV",
  "Inventario": 138
 },
 {
  "Estado": "activa",
  "Fecha_inicio": "12\/08\/2023",
  "Fecha_fin": "12\/31\/2023",
  "SKU": 104409800,
  "para_quien": "Secret Santa",
  "edad": "Joven",
  "presupuesto": "100+",
  "categoria": "Tecnologia",
  "Nombre": "TV LED SMART 32\" A PRO HD - GOOGLE TV",
  "Descuento": "29.7%",
  "img": "https:\/\/siman.vtexassets.com\/arquivos\/ids\/4958748-1600-auto?v=638361792585130000&width=1600&height=auto&aspect=true",
  "url": "https:\/\/sv.siman.com\/tv-smart-32-a-pro-hd-1366-x-768-60-hz-104409800\/p",
  "Precio_regular": 269,
  "Precio_promocion": 189,
  "Pais": "SV",
  "Inventario": 201
 },
 {
  "Estado": "activa",
  "Fecha_inicio": "12\/08\/2023",
  "Fecha_fin": "12\/31\/2023",
  "SKU": 104050063,
  "para_quien": "Secret Santa",
  "edad": "Joven",
  "presupuesto": "100+",
  "categoria": "Tecnologia",
  "Nombre": "TV LED SMART 32\" HD ANDROID",
  "Descuento": "27.4%",
  "img": "https:\/\/siman.vtexassets.com\/arquivos\/ids\/3892327-1600-auto?v=638108790822200000&width=1600&height=auto&aspect=true",
  "url": "https:\/\/sv.siman.com\/tv-led-smart-32-hd-android-104050063\/p",
  "Precio_regular": 219,
  "Precio_promocion": 159,
  "Pais": "SV",
  "Inventario": 66
 },
 {
  "Estado": "activa",
  "Fecha_inicio": "12\/08\/2023",
  "Fecha_fin": "12\/31\/2023",
  "SKU": 104048314,
  "para_quien": "Secret Santa",
  "edad": "Joven",
  "presupuesto": "100+",
  "categoria": "Tecnologia",
  "Nombre": "TV LED SMART 32\" HD ROKU",
  "Descuento": "20.1%",
  "img": "https:\/\/siman.vtexassets.com\/arquivos\/ids\/3892309-1600-auto?v=638108790774700000&width=1600&height=auto&aspect=true",
  "url": "https:\/\/sv.siman.com\/tv-led-smart-32-hd-roku-104048314\/p",
  "Precio_regular": 199,
  "Precio_promocion": 159,
  "Pais": "SV",
  "Inventario": 87
 },
 {
  "Estado": "activa",
  "Fecha_inicio": "12\/08\/2023",
  "Fecha_fin": "12\/31\/2023",
  "SKU": 104069685,
  "para_quien": "Secret Santa",
  "edad": "Adulto",
  "presupuesto": 50,
  "categoria": "Tecnologia",
  "Nombre": "AUDIFONO BT ON EAR JUNIOR 310 AZUL",
  "Descuento": "0.0%",
  "img": "https:\/\/siman.vtexassets.com\/arquivos\/ids\/3936515-1600-auto?v=638120876881730000&width=1600&height=auto&aspect=true",
  "url": "https:\/\/sv.siman.com\/audifonos-bt-junior-310-kids-azul-104069685\/p",
  "Precio_regular": 59,
  "Precio_promocion": 59,
  "Pais": "SV",
  "Inventario": 81
 },
 {
  "Estado": "activa",
  "Fecha_inicio": "12\/08\/2023",
  "Fecha_fin": "12\/31\/2023",
  "SKU": 104154291,
  "para_quien": "Secret Santa",
  "edad": "Adulto",
  "presupuesto": 50,
  "categoria": "Tecnologia",
  "Nombre": "AUDIFONO BT ON EAR JUNIOR 310 ROJO",
  "Descuento": "0.0%",
  "img": "https:\/\/siman.vtexassets.com\/arquivos\/ids\/4205454-1600-auto?v=638186552675000000&width=1600&height=auto&aspect=true",
  "url": "https:\/\/sv.siman.com\/audifono-gaming-para-nios-104154291\/p",
  "Precio_regular": 59,
  "Precio_promocion": 59,
  "Pais": "SV",
  "Inventario": 14
 },
 {
  "Estado": "activa",
  "Fecha_inicio": "12\/08\/2023",
  "Fecha_fin": "12\/31\/2023",
  "SKU": 104069682,
  "para_quien": "Secret Santa",
  "edad": "Adulto",
  "presupuesto": 50,
  "categoria": "Tecnologia",
  "Nombre": "AUDIFONO BT ON EAR JUNIOR 310 VERDE",
  "Descuento": "0.0%",
  "img": "https:\/\/siman.vtexassets.com\/arquivos\/ids\/3936501-1600-auto?v=638120876843200000&width=1600&height=auto&aspect=true",
  "url": "https:\/\/sv.siman.com\/audifonos-bt-junior-310-kids-green-104069682\/p",
  "Precio_regular": 59,
  "Precio_promocion": 59,
  "Pais": "SV",
  "Inventario": 89
 },
 {
  "Estado": "activa",
  "Fecha_inicio": "12\/08\/2023",
  "Fecha_fin": "12\/31\/2023",
  "SKU": 104084780,
  "para_quien": "Secret Santa",
  "edad": "Adulto",
  "presupuesto": 100,
  "categoria": "Tecnologia",
  "Nombre": "AUDIFONO BT TRUE WIRELESS VIBE BEAM BEIGE",
  "Descuento": "0.0%",
  "img": "https:\/\/siman.vtexassets.com\/arquivos\/ids\/4016254-1600-auto?v=638138958556570000&width=1600&height=auto&aspect=true",
  "url": "https:\/\/sv.siman.com\/audifono-bt-true-wireless-vibe-beam-begam-104084780\/p",
  "Precio_regular": 64,
  "Precio_promocion": 64,
  "Pais": "SV",
  "Inventario": 40
 },
 {
  "Estado": "activa",
  "Fecha_inicio": "12\/08\/2023",
  "Fecha_fin": "12\/31\/2023",
  "SKU": 104084778,
  "para_quien": "Secret Santa",
  "edad": "Adulto",
  "presupuesto": 100,
  "categoria": "Tecnologia",
  "Nombre": "AUDIFONO BT TRUE WIRELESS VIBE BEAM BLANCO",
  "Descuento": "0.0%",
  "img": "https:\/\/siman.vtexassets.com\/arquivos\/ids\/4016242-1600-auto?v=638138958526300000&width=1600&height=auto&aspect=true",
  "url": "https:\/\/sv.siman.com\/audifono-bt-true-wireless-vibe-beam-blanco-104084778\/p",
  "Precio_regular": 64,
  "Precio_promocion": 64,
  "Pais": "SV",
  "Inventario": 28
 },
 {
  "Estado": "activa",
  "Fecha_inicio": "12\/08\/2023",
  "Fecha_fin": "12\/31\/2023",
  "SKU": 104084779,
  "para_quien": "Secret Santa",
  "edad": "Adulto",
  "presupuesto": 100,
  "categoria": "Tecnologia",
  "Nombre": "AUDIFONO BT TRUE WIRELESS VIBE BEAM MENTA",
  "Descuento": "0.0%",
  "img": "https:\/\/siman.vtexassets.com\/arquivos\/ids\/4016248-1600-auto?v=638138958542800000&width=1600&height=auto&aspect=true",
  "url": "https:\/\/sv.siman.com\/audifono-bt-true-wireless-vibe-beam-menta-104084779\/p",
  "Precio_regular": 64,
  "Precio_promocion": 64,
  "Pais": "SV",
  "Inventario": 34
 },
 {
  "Estado": "activa",
  "Fecha_inicio": "12\/08\/2023",
  "Fecha_fin": "12\/31\/2023",
  "SKU": 104269684,
  "para_quien": "Secret Santa",
  "edad": "Adulto",
  "presupuesto": 50,
  "categoria": "Tecnologia",
  "Nombre": "AUDIFONO BT TRUE WIRELESS VIBE BUDS BEIGE",
  "Descuento": "0.0%",
  "img": "https:\/\/siman.vtexassets.com\/arquivos\/ids\/4574256-1600-auto?v=638279098433200000&width=1600&height=auto&aspect=true",
  "url": "https:\/\/sv.siman.com\/audifono-bt-true-wireless-vibe-buds-beige-104269684\/p",
  "Precio_regular": 54,
  "Precio_promocion": 54,
  "Pais": "SV",
  "Inventario": 26
 },
 {
  "Estado": "activa",
  "Fecha_inicio": "12\/08\/2023",
  "Fecha_fin": "12\/31\/2023",
  "SKU": 104084775,
  "para_quien": "Secret Santa",
  "edad": "Adulto",
  "presupuesto": 50,
  "categoria": "Tecnologia",
  "Nombre": "AUDIFONO BT TRUE WIRELESS VIBE BUDS BLANCOS",
  "Descuento": "0.0%",
  "img": "https:\/\/siman.vtexassets.com\/arquivos\/ids\/4016224-1600-auto?v=638138958480830000&width=1600&height=auto&aspect=true",
  "url": "https:\/\/sv.siman.com\/audifono-bt-true-wireless-vibe-buds-blancos-104084775\/p",
  "Precio_regular": 54,
  "Precio_promocion": 54,
  "Pais": "SV",
  "Inventario": 18
 },
 {
  "Estado": "activa",
  "Fecha_inicio": "12\/08\/2023",
  "Fecha_fin": "12\/31\/2023",
  "SKU": 104084776,
  "para_quien": "Secret Santa",
  "edad": "Adulto",
  "presupuesto": 50,
  "categoria": "Tecnologia",
  "Nombre": "AUDIFONO BT TRUE WIRELESS VIBE BUDS MENTA",
  "Descuento": "0.0%",
  "img": "https:\/\/siman.vtexassets.com\/arquivos\/ids\/4016231-1600-auto?v=638138958497100000&width=1600&height=auto&aspect=true",
  "url": "https:\/\/sv.siman.com\/audifono-bt-true-wireless-vibe-buds-menta-104084776\/p",
  "Precio_regular": 54,
  "Precio_promocion": 54,
  "Pais": "SV",
  "Inventario": 25
 },
 {
  "Estado": "activa",
  "Fecha_inicio": "12\/08\/2023",
  "Fecha_fin": "12\/31\/2023",
  "SKU": 104087647,
  "para_quien": "Secret Santa",
  "edad": "Adulto",
  "presupuesto": 50,
  "categoria": "Tecnologia",
  "Nombre": "AUDIFONO BT TRUE WIRELESS VIBE BUDS NEGROS",
  "Descuento": "0.0%",
  "img": "https:\/\/siman.vtexassets.com\/arquivos\/ids\/4016270-1600-auto?v=638138958593400000&width=1600&height=auto&aspect=true",
  "url": "https:\/\/sv.siman.com\/audifono-bt-true-wireless-vibe-buds-negros-104087647\/p",
  "Precio_regular": 54,
  "Precio_promocion": 54,
  "Pais": "SV",
  "Inventario": 178
 },
 {
  "Estado": "activa",
  "Fecha_inicio": "12\/08\/2023",
  "Fecha_fin": "12\/31\/2023",
  "SKU": 104084781,
  "para_quien": "Secret Santa",
  "edad": "Adulto",
  "presupuesto": 25,
  "categoria": "Tecnologia",
  "Nombre": "AUDIFONO IN EAR BT ENDURANCE RUN AMARILLO\/GRIS",
  "Descuento": "0.0%",
  "img": "https:\/\/siman.vtexassets.com\/arquivos\/ids\/4016263-1600-auto?v=638138958576870000&width=1600&height=auto&aspect=true",
  "url": "https:\/\/sv.siman.com\/audifono-in-ear-bt-endurance-run-amarillo-gris-104084781\/p",
  "Precio_regular": 25.9,
  "Precio_promocion": 25.9,
  "Pais": "SV",
  "Inventario": 184
 },
 {
  "Estado": "activa",
  "Fecha_inicio": "12\/08\/2023",
  "Fecha_fin": "12\/31\/2023",
  "SKU": 104362367,
  "para_quien": "Secret Santa",
  "edad": "Adulto",
  "presupuesto": 25,
  "categoria": "Tecnologia",
  "Nombre": "AUDIFONO IN EAR BT ENDURANCE RUN AZUL",
  "Descuento": "0.0%",
  "img": "https:\/\/siman.vtexassets.com\/arquivos\/ids\/4763104-1600-auto?v=638321113680270000&width=1600&height=auto&aspect=true",
  "url": "https:\/\/sv.siman.com\/audifono-in-ear-bt-endurance-run-azul-104362367\/p",
  "Precio_regular": 25.9,
  "Precio_promocion": 25.9,
  "Pais": "SV",
  "Inventario": 226
 },
 {
  "Estado": "activa",
  "Fecha_inicio": "12\/08\/2023",
  "Fecha_fin": "12\/31\/2023",
  "SKU": 104206612,
  "para_quien": "Secret Santa",
  "edad": "Adulto",
  "presupuesto": 25,
  "categoria": "Tecnologia",
  "Nombre": "AUDIFONO IN EAR REDMI BUDS 4 LITE BLANCO",
  "Descuento": "0.0%",
  "img": "https:\/\/siman.vtexassets.com\/arquivos\/ids\/4410666-1600-auto?v=638237402493730000&width=1600&height=auto&aspect=true",
  "url": "https:\/\/sv.siman.com\/audifono-in-ear-redmi-buds-4-lite-blanco-104206612\/p",
  "Precio_regular": 29,
  "Precio_promocion": 29,
  "Pais": "SV",
  "Inventario": 509
 },
 {
  "Estado": "activa",
  "Fecha_inicio": "12\/08\/2023",
  "Fecha_fin": "12\/31\/2023",
  "SKU": 104206611,
  "para_quien": "Secret Santa",
  "edad": "Adulto",
  "presupuesto": 25,
  "categoria": "Tecnologia",
  "Nombre": "AUDIFONO IN EAR REDMI BUDS 4 LITE NEGRO",
  "Descuento": "0.0%",
  "img": "https:\/\/siman.vtexassets.com\/arquivos\/ids\/4410661-1600-auto?v=638237402477430000&width=1600&height=auto&aspect=true",
  "url": "https:\/\/sv.siman.com\/audifono-in-ear-redmi-buds-4-lite-negro-104206611\/p",
  "Precio_regular": 29,
  "Precio_promocion": 29,
  "Pais": "SV",
  "Inventario": 905
 },
 {
  "Estado": "activa",
  "Fecha_inicio": "12\/08\/2023",
  "Fecha_fin": "12\/31\/2023",
  "SKU": 104094139,
  "para_quien": "Secret Santa",
  "edad": "Adulto",
  "presupuesto": 100,
  "categoria": "Tecnologia",
  "Nombre": "AUDIFONO IN EAR TWS REDMI BUDS 4 PRO BLANCOS",
  "Descuento": "30.3%",
  "img": "https:\/\/siman.vtexassets.com\/arquivos\/ids\/4014550-1600-auto?v=638138288437070000&width=1600&height=auto&aspect=true",
  "url": "https:\/\/sv.siman.com\/audifono-in-ear-tws-redmi-buds-4-pro-blancos-104094139\/p",
  "Precio_regular": 99,
  "Precio_promocion": 69,
  "Pais": "SV",
  "Inventario": 88
 },
 {
  "Estado": "activa",
  "Fecha_inicio": "12\/08\/2023",
  "Fecha_fin": "12\/31\/2023",
  "SKU": 104094138,
  "para_quien": "Secret Santa",
  "edad": "Adulto",
  "presupuesto": 100,
  "categoria": "Tecnologia",
  "Nombre": "AUDIFONO IN EAR TWS REDMI BUDS 4 PRO NEGROS",
  "Descuento": "30.3%",
  "img": "https:\/\/siman.vtexassets.com\/arquivos\/ids\/4014545-1600-auto?v=638138288424400000&width=1600&height=auto&aspect=true",
  "url": "https:\/\/sv.siman.com\/audifono-in-ear-tws-redmi-buds-4-pro-negros-104094138\/p",
  "Precio_regular": 99,
  "Precio_promocion": 69,
  "Pais": "SV",
  "Inventario": 51
 },
 {
  "Estado": "activa",
  "Fecha_inicio": "12\/08\/2023",
  "Fecha_fin": "12\/31\/2023",
  "SKU": 101201415,
  "para_quien": "Secret Santa",
  "edad": "Adulto",
  "presupuesto": 25,
  "categoria": "Tecnologia",
  "Nombre": "AUDIFONOS CON MICROFONO INTRAURALES T110 AZULES",
  "Descuento": "0.0%",
  "img": "https:\/\/siman.vtexassets.com\/arquivos\/ids\/325421-1600-auto?v=637250606445430000&width=1600&height=auto&aspect=true",
  "url": "https:\/\/sv.siman.com\/audifono-jbl-tune-110-azules-101201415\/p",
  "Precio_regular": 14.9,
  "Precio_promocion": 14.9,
  "Pais": "SV",
  "Inventario": 249
 },
 {
  "Estado": "activa",
  "Fecha_inicio": "12\/08\/2023",
  "Fecha_fin": "12\/31\/2023",
  "SKU": 101201413,
  "para_quien": "Secret Santa",
  "edad": "Adulto",
  "presupuesto": 25,
  "categoria": "Tecnologia",
  "Nombre": "AUDIFONOS CON MICROFONO INTRAURALES T110 BLANCOS",
  "Descuento": "0.0%",
  "img": "https:\/\/siman.vtexassets.com\/arquivos\/ids\/325420-1600-auto?v=637250606440600000&width=1600&height=auto&aspect=true",
  "url": "https:\/\/sv.siman.com\/audifono-jbl-tune-110-blancos-101201413\/p",
  "Precio_regular": 14.9,
  "Precio_promocion": 14.9,
  "Pais": "SV",
  "Inventario": 229
 },
 {
  "Estado": "activa",
  "Fecha_inicio": "12\/08\/2023",
  "Fecha_fin": "12\/31\/2023",
  "SKU": 100783980,
  "para_quien": "Secret Santa",
  "edad": "Adulto",
  "presupuesto": 25,
  "categoria": "Tecnologia",
  "Nombre": "AUDIFONOS CON MICROFONO INTRAURALES T110 NEGRO",
  "Descuento": "0.0%",
  "img": "https:\/\/siman.vtexassets.com\/arquivos\/ids\/3865688-1600-auto?v=638101760048430000&width=1600&height=auto&aspect=true",
  "url": "https:\/\/sv.siman.com\/audifono-in-ear-con-microfono-y-cable-flat-negros-100783980\/p",
  "Precio_regular": 14.9,
  "Precio_promocion": 14.9,
  "Pais": "SV",
  "Inventario": 375
 },
 {
  "Estado": "activa",
  "Fecha_inicio": "12\/08\/2023",
  "Fecha_fin": "12\/31\/2023",
  "SKU": 104154277,
  "para_quien": "Secret Santa",
  "edad": "Adulto",
  "presupuesto": 100,
  "categoria": "Tecnologia",
  "Nombre": "AUDIFONOS ON EAR BT CON MICRONOFO AZUL",
  "Descuento": "28.3%",
  "img": "https:\/\/siman.vtexassets.com\/arquivos\/ids\/4205378-1600-auto?v=638186552498400000&width=1600&height=auto&aspect=true",
  "url": "https:\/\/sv.siman.com\/audifono-de-diadema-wh-ch520-inalambrico-bt-azul-104154277\/p",
  "Precio_regular": 64,
  "Precio_promocion": 45.9,
  "Pais": "SV",
  "Inventario": 320
 },
 {
  "Estado": "activa",
  "Fecha_inicio": "12\/08\/2023",
  "Fecha_fin": "12\/31\/2023",
  "SKU": 104154278,
  "para_quien": "Secret Santa",
  "edad": "Adulto",
  "presupuesto": 100,
  "categoria": "Tecnologia",
  "Nombre": "AUDIFONOS ON EAR BT CON MICRONOFO BEIGE",
  "Descuento": "28.3%",
  "img": "https:\/\/siman.vtexassets.com\/arquivos\/ids\/4205386-1600-auto?v=638186552514870000&width=1600&height=auto&aspect=true",
  "url": "https:\/\/sv.siman.com\/audifono-de-diadema-wh-ch520-inalambrico-bt-beige-104154278\/p",
  "Precio_regular": 64,
  "Precio_promocion": 45.9,
  "Pais": "SV",
  "Inventario": 30
 },
 {
  "Estado": "activa",
  "Fecha_inicio": "12\/08\/2023",
  "Fecha_fin": "12\/31\/2023",
  "SKU": 103670922,
  "para_quien": "Secret Santa",
  "edad": "Adulto",
  "presupuesto": "100+",
  "categoria": "Tecnologia",
  "Nombre": "BOCINA INALAMBRICA FLIP6 ESTEREO NEGRA",
  "Descuento": "20.1%",
  "img": "https:\/\/siman.vtexassets.com\/arquivos\/ids\/2758617-1600-auto?v=637843653236770000&width=1600&height=auto&aspect=true",
  "url": "https:\/\/sv.siman.com\/bocina-inalambrica-flip6-estereo-negra-103670922\/p",
  "Precio_regular": 149,
  "Precio_promocion": 119,
  "Pais": "SV",
  "Inventario": 22
 },
 {
  "Estado": "activa",
  "Fecha_inicio": "12\/08\/2023",
  "Fecha_fin": "12\/31\/2023",
  "SKU": 103913429,
  "para_quien": "Secret Santa",
  "edad": "Adulto",
  "presupuesto": "100+",
  "categoria": "Tecnologia",
  "Nombre": "BOCINA INALAMBRICA FLIP6 ESTEREO ROSA",
  "Descuento": "20.1%",
  "img": "https:\/\/siman.vtexassets.com\/arquivos\/ids\/3421447-1600-auto?v=637999831576400000&width=1600&height=auto&aspect=true",
  "url": "https:\/\/sv.siman.com\/jbl-speaker-bt-flip-6-pink-103913429\/p",
  "Precio_regular": 149,
  "Precio_promocion": 119,
  "Pais": "SV",
  "Inventario": 24
 },
 {
  "Estado": "activa",
  "Fecha_inicio": "12\/08\/2023",
  "Fecha_fin": "12\/31\/2023",
  "SKU": 104062501,
  "para_quien": "Secret Santa",
  "edad": "Adulto",
  "presupuesto": "100+",
  "categoria": "Tecnologia",
  "Nombre": "BOCINA INALAMBRICA FLIP6 ESTEREO VERDE",
  "Descuento": "20.1%",
  "img": "https:\/\/siman.vtexassets.com\/arquivos\/ids\/3935145-1600-auto?v=638120634689270000&width=1600&height=auto&aspect=true",
  "url": "https:\/\/sv.siman.com\/bocina-inalambrica-flip6-estereo-verde-104062501\/p",
  "Precio_regular": 149,
  "Precio_promocion": 119,
  "Pais": "SV",
  "Inventario": 90
 },
 {
  "Estado": "activa",
  "Fecha_inicio": "12\/08\/2023",
  "Fecha_fin": "12\/31\/2023",
  "SKU": 104372962,
  "para_quien": "Secret Santa",
  "edad": "Adulto",
  "presupuesto": 50,
  "categoria": "Tecnologia",
  "Nombre": "BOCINA SMART AMAZON ECHO AUTO INALÁMBRICA NEGRA",
  "Descuento": "0.0%",
  "img": "https:\/\/siman.vtexassets.com\/arquivos\/ids\/4789428-1600-auto?v=638326565858070000&width=1600&height=auto&aspect=true",
  "url": "https:\/\/sv.siman.com\/bocina-smart-amazon-echo-auto-inalambrica-negra-104372962\/p",
  "Precio_regular": 39,
  "Precio_promocion": 39,
  "Pais": "SV",
  "Inventario": 14
 },
 {
  "Estado": "activa",
  "Fecha_inicio": "12\/08\/2023",
  "Fecha_fin": "12\/31\/2023",
  "SKU": 104265789,
  "para_quien": "Secret Santa",
  "edad": "Adulto",
  "presupuesto": 100,
  "categoria": "Tecnologia",
  "Nombre": "BOCINA SMART AMAZON ECHO DOT 5TA GEN KID BÚHO",
  "Descuento": "17.3%",
  "img": "https:\/\/siman.vtexassets.com\/arquivos\/ids\/4596555-1600-auto?v=638284228091470000&width=1600&height=auto&aspect=true",
  "url": "https:\/\/sv.siman.com\/bocina-smart-amazon-echo-dot-5ta-gen-kid-buho-104265789\/p",
  "Precio_regular": 75,
  "Precio_promocion": 62,
  "Pais": "SV",
  "Inventario": 17
 },
 {
  "Estado": "activa",
  "Fecha_inicio": "12\/08\/2023",
  "Fecha_fin": "12\/31\/2023",
  "SKU": 104265790,
  "para_quien": "Secret Santa",
  "edad": "Adulto",
  "presupuesto": 100,
  "categoria": "Tecnologia",
  "Nombre": "BOCINA SMART AMAZON ECHO DOT 5TA GEN KID DRAGÓN",
  "Descuento": "17.3%",
  "img": "https:\/\/siman.vtexassets.com\/arquivos\/ids\/4596559-1600-auto?v=638284228130270000&width=1600&height=auto&aspect=true",
  "url": "https:\/\/sv.siman.com\/bocina-smart-amazon-echo-dot-5ta-gen-kid-dragon-104265790\/p",
  "Precio_regular": 75,
  "Precio_promocion": 62,
  "Pais": "SV",
  "Inventario": 20
 },
 {
  "Estado": "activa",
  "Fecha_inicio": "12\/08\/2023",
  "Fecha_fin": "12\/31\/2023",
  "SKU": 104045122,
  "para_quien": "Secret Santa",
  "edad": "Adulto",
  "presupuesto": 100,
  "categoria": "Tecnologia",
  "Nombre": "BOCINA SMART AMAZON ECHO DOT AZUL 5TA GEN",
  "Descuento": "19.0%",
  "img": "https:\/\/siman.vtexassets.com\/arquivos\/ids\/3936412-1600-auto?v=638120876591770000&width=1600&height=auto&aspect=true",
  "url": "https:\/\/sv.siman.com\/bocina-smart-amazon-echo-dot-azul-4ta-gen-104045122\/p",
  "Precio_regular": 79,
  "Precio_promocion": 64,
  "Pais": "SV",
  "Inventario": 83
 },
 {
  "Estado": "activa",
  "Fecha_inicio": "12\/08\/2023",
  "Fecha_fin": "12\/31\/2023",
  "SKU": 104045120,
  "para_quien": "Secret Santa",
  "edad": "Adulto",
  "presupuesto": 100,
  "categoria": "Tecnologia",
  "Nombre": "BOCINA SMART AMAZON ECHO DOT NEGRA 5TA GEN",
  "Descuento": "19.0%",
  "img": "https:\/\/siman.vtexassets.com\/arquivos\/ids\/3936405-1600-auto?v=638120876569730000&width=1600&height=auto&aspect=true",
  "url": "https:\/\/sv.siman.com\/bocina-smart-amazon-echo-dot-negra-5ta-gen-104045120\/p",
  "Precio_regular": 79,
  "Precio_promocion": 64,
  "Pais": "SV",
  "Inventario": 119
 },
 {
  "Estado": "activa",
  "Fecha_inicio": "12\/08\/2023",
  "Fecha_fin": "12\/31\/2023",
  "SKU": 103844798,
  "para_quien": "Secret Santa",
  "edad": "Adulto",
  "presupuesto": "100+",
  "categoria": "Tecnologia",
  "Nombre": "JBL CHARGE 5 PARLANTE COLOR AQUA",
  "Descuento": "21.2%",
  "img": "https:\/\/siman.vtexassets.com\/arquivos\/ids\/3245686-1600-auto?v=637964335318100000&width=1600&height=auto&aspect=true",
  "url": "https:\/\/sv.siman.com\/bocina-bt-charge-5-103844798\/p",
  "Precio_regular": 189,
  "Precio_promocion": 149,
  "Pais": "SV",
  "Inventario": 30
 },
 {
  "Estado": "activa",
  "Fecha_inicio": "12\/08\/2023",
  "Fecha_fin": "12\/31\/2023",
  "SKU": 103351228,
  "para_quien": "Secret Santa",
  "edad": "Adulto",
  "presupuesto": "100+",
  "categoria": "Tecnologia",
  "Nombre": "JBL CHARGE 5 PARLANTE COLOR AZUL",
  "Descuento": "21.2%",
  "img": "https:\/\/siman.vtexassets.com\/arquivos\/ids\/1495991-1600-auto?v=637598890198870000&width=1600&height=auto&aspect=true",
  "url": "https:\/\/sv.siman.com\/jbl-charge-5-parlante-color-azul-103351228\/p",
  "Precio_regular": 189,
  "Precio_promocion": 149,
  "Pais": "SV",
  "Inventario": 43
 },
 {
  "Estado": "activa",
  "Fecha_inicio": "12\/08\/2023",
  "Fecha_fin": "12\/31\/2023",
  "SKU": 104050128,
  "para_quien": "Secret Santa",
  "edad": "Adulto",
  "presupuesto": "100+",
  "categoria": "Tecnologia",
  "Nombre": "JBL CHARGE 5 PARLANTE COLOR GRIS",
  "Descuento": "21.2%",
  "img": "https:\/\/siman.vtexassets.com\/arquivos\/ids\/3892344-1600-auto?v=638108790870270000&width=1600&height=auto&aspect=true",
  "url": "https:\/\/sv.siman.com\/bocina-portatil-charge-5-gris-104050128\/p",
  "Precio_regular": 189,
  "Precio_promocion": 149,
  "Pais": "SV",
  "Inventario": 53
 },
 {
  "Estado": "activa",
  "Fecha_inicio": "12\/08\/2023",
  "Fecha_fin": "12\/31\/2023",
  "SKU": 104218095,
  "para_quien": "Secret Santa",
  "edad": "Adulto",
  "presupuesto": 100,
  "categoria": "Tecnologia",
  "Nombre": "REPRODUCTOR MULTIMEDIA CHROMECAST CON GOOGLE TV HD",
  "Descuento": "0.0%",
  "img": "https:\/\/siman.vtexassets.com\/arquivos\/ids\/4411055-1600-auto?v=638237403857600000&width=1600&height=auto&aspect=true",
  "url": "https:\/\/sv.siman.com\/reproductor-multimedia-chromecast-con-google-tv-hd-104218095\/p",
  "Precio_regular": 59,
  "Precio_promocion": 59,
  "Pais": "SV",
  "Inventario": 67
 },
 {
  "Estado": "activa",
  "Fecha_inicio": "12\/08\/2023",
  "Fecha_fin": "12\/31\/2023",
  "SKU": 103631672,
  "para_quien": "Secret Santa",
  "edad": "Adulto",
  "presupuesto": 100,
  "categoria": "Tecnologia",
  "Nombre": "REPRODUCTOR MULTIMEDIA FIRE TV STICK HD 3RA. GEN. ALEXA",
  "Descuento": "23.2%",
  "img": "https:\/\/siman.vtexassets.com\/arquivos\/ids\/2638304-1600-auto?v=637810725118930000&width=1600&height=auto&aspect=true",
  "url": "https:\/\/sv.siman.com\/reproductor-multimedia-fire-tv-stick-hd-3ra-gen-alexa-103631672\/p",
  "Precio_regular": 65,
  "Precio_promocion": 49.9,
  "Pais": "SV",
  "Inventario": 209
 },
 {
  "Estado": "activa",
  "Fecha_inicio": "12\/08\/2023",
  "Fecha_fin": "12\/31\/2023",
  "SKU": 103631673,
  "para_quien": "Secret Santa",
  "edad": "Adulto",
  "presupuesto": 100,
  "categoria": "Tecnologia",
  "Nombre": "REPRODUCTOR MULTIMEDIA FIRE TV STICK UHD 4K ALEXA",
  "Descuento": "0.0%",
  "img": "https:\/\/siman.vtexassets.com\/arquivos\/ids\/2638307-1600-auto?v=637810725126270000&width=1600&height=auto&aspect=true",
  "url": "https:\/\/sv.siman.com\/reproductor-multimedia-fire-tv-stick-uhd-4k-alexa-103631673\/p",
  "Precio_regular": 69,
  "Precio_promocion": 69,
  "Pais": "SV",
  "Inventario": 47
 },
 {
  "Estado": "activa",
  "Fecha_inicio": "12\/08\/2023",
  "Fecha_fin": "12\/31\/2023",
  "SKU": 104372964,
  "para_quien": "Secret Santa",
  "edad": "Adulto",
  "presupuesto": 100,
  "categoria": "Tecnologia",
  "Nombre": "REPRODUCTOR MULTIMEDIA FIRE TV STICK UHD 4K MAX ALEXA",
  "Descuento": "0.0%",
  "img": "https:\/\/siman.vtexassets.com\/arquivos\/ids\/4789436-1600-auto?v=638326565883370000&width=1600&height=auto&aspect=true",
  "url": "https:\/\/sv.siman.com\/reproductor-multimedia-fire-tv-stick-uhd-4k-max-alexa-104372964\/p",
  "Precio_regular": 69,
  "Precio_promocion": 69,
  "Pais": "SV",
  "Inventario": 107
 },
 {
  "Estado": "activa",
  "Fecha_inicio": "12\/08\/2023",
  "Fecha_fin": "12\/31\/2023",
  "SKU": 104215432,
  "para_quien": "Secret Santa",
  "edad": "Adulto",
  "presupuesto": 100,
  "categoria": "Tecnologia",
  "Nombre": "REPRODUCTOR MULTIMEDIA MI TV STICK 4K",
  "Descuento": "14.5%",
  "img": "https:\/\/siman.vtexassets.com\/arquivos\/ids\/4410858-800-auto?v=638237403148700000&width=800&height=auto&aspect=true",
  "url": "https:\/\/sv.siman.com\/reproductor-multimedia-mi-tv-stick-4k-104215432\/p",
  "Precio_regular": 69,
  "Precio_promocion": 59,
  "Pais": "SV",
  "Inventario": 138
 },
 {
  "Estado": "activa",
  "Fecha_inicio": "12\/08\/2023",
  "Fecha_fin": "12\/31\/2023",
  "SKU": 104409800,
  "para_quien": "Secret Santa",
  "edad": "Adulto",
  "presupuesto": "100+",
  "categoria": "Tecnologia",
  "Nombre": "TV LED SMART 32\" A PRO HD - GOOGLE TV",
  "Descuento": "29.7%",
  "img": "https:\/\/siman.vtexassets.com\/arquivos\/ids\/4958748-1600-auto?v=638361792585130000&width=1600&height=auto&aspect=true",
  "url": "https:\/\/sv.siman.com\/tv-smart-32-a-pro-hd-1366-x-768-60-hz-104409800\/p",
  "Precio_regular": 269,
  "Precio_promocion": 189,
  "Pais": "SV",
  "Inventario": 201
 },
 {
  "Estado": "activa",
  "Fecha_inicio": "12\/08\/2023",
  "Fecha_fin": "12\/31\/2023",
  "SKU": 104050063,
  "para_quien": "Secret Santa",
  "edad": "Adulto",
  "presupuesto": "100+",
  "categoria": "Tecnologia",
  "Nombre": "TV LED SMART 32\" HD ANDROID",
  "Descuento": "27.4%",
  "img": "https:\/\/siman.vtexassets.com\/arquivos\/ids\/3892327-1600-auto?v=638108790822200000&width=1600&height=auto&aspect=true",
  "url": "https:\/\/sv.siman.com\/tv-led-smart-32-hd-android-104050063\/p",
  "Precio_regular": 219,
  "Precio_promocion": 159,
  "Pais": "SV",
  "Inventario": 66
 },
 {
  "Estado": "activa",
  "Fecha_inicio": "12\/08\/2023",
  "Fecha_fin": "12\/31\/2023",
  "SKU": 104048314,
  "para_quien": "Secret Santa",
  "edad": "Adulto",
  "presupuesto": "100+",
  "categoria": "Tecnologia",
  "Nombre": "TV LED SMART 32\" HD ROKU",
  "Descuento": "20.1%",
  "img": "https:\/\/siman.vtexassets.com\/arquivos\/ids\/3892309-1600-auto?v=638108790774700000&width=1600&height=auto&aspect=true",
  "url": "https:\/\/sv.siman.com\/tv-led-smart-32-hd-roku-104048314\/p",
  "Precio_regular": 199,
  "Precio_promocion": 159,
  "Pais": "SV",
  "Inventario": 87
 },
 {
  "Estado": "activa",
  "Fecha_inicio": "08\/12\/2023",
  "Fecha_fin": "24\/12\/2023",
  "SKU": 413489500006,
  "para_quien": "Secret Santa",
  "edad": "Adulto",
  "categoria": "Tecnologia",
  "img": "https:\/\/siman.vtexassets.com\/arquivos\/ids\/1492509-1600-auto?v=637596459927330000&width=1600&height=auto&aspect=true",
  "url": "https:\/\/sv.siman.com\/grill-sandwichera-134895\/p",
  "Precio_regular": 95.9,
  "Precio_promocion": 59.99,
  "Pais": "SV",
  "Inventario": 126
 },
 {
  "Estado": "activa",
  "Fecha_inicio": "08\/12\/2023",
  "Fecha_fin": "24\/12\/2023",
  "SKU": 103201297,
  "para_quien": "Secret Santa",
  "edad": "Adulto",
  "img": "https:\/\/siman.vtexassets.com\/arquivos\/ids\/1492470-1600-auto?v=637596459838630000&width=1600&height=auto&aspect=true ",
  "url": "https:\/\/sv.siman.com\/wafflera-760-wt-placas-antiadherente-103201297\/p",
  "Precio_regular": 33.9,
  "Precio_promocion": 22,
  "Pais": "SV",
  "Inventario": 161
 },
 {
  "Estado": "activa",
  "Fecha_inicio": "08\/12\/2023",
  "Fecha_fin": "24\/12\/2023",
  "SKU": 101955844,
  "para_quien": "Secret Santa",
  "edad": "Adulto",
  "img": "https:\/\/siman.vtexassets.com\/arquivos\/ids\/1491922-1600-auto?v=637596458458700000&width=1600&height=auto&aspect=true",
  "url": "https:\/\/sv.siman.com\/horno-black-decker-101955844\/p ",
  "Precio_regular": 54.9,
  "Precio_promocion": 39.99,
  "Pais": "SV",
  "Inventario": 541
 },
 {
  "Estado": "activa",
  "Fecha_inicio": "08\/12\/2023",
  "Fecha_fin": "24\/12\/2023",
  "SKU": 101474455,
  "para_quien": "Secret Santa",
  "edad": "Adulto",
  "img": "https:\/\/siman.vtexassets.com\/arquivos\/ids\/1491765-1600-auto?v=637596458072300000&width=1600&height=auto&aspect=true",
  "url": "https:\/\/sv.siman.com\/horno-con-conveccion-4-rebanadas-101474455\/p",
  "Precio_regular": 82.9,
  "Precio_promocion": 62,
  "Pais": "SV",
  "Inventario": 658
 },
 {
  "Estado": "activa",
  "Fecha_inicio": "08\/12\/2023",
  "Fecha_fin": "24\/12\/2023",
  "SKU": 103679934,
  "para_quien": "Secret Santa",
  "edad": "Adulto",
  "img": "https:\/\/siman.vtexassets.com\/arquivos\/ids\/4804921-1600-auto?v=638330666900000000&width=1600&height=auto&aspect=true",
  "url": "https:\/\/sv.siman.com\/freidora-de-aire-4-l-negra-103679934\/p",
  "Precio_regular": 119.9,
  "Precio_promocion": 89.99,
  "Pais": "SV",
  "Inventario": 260
 },
 {
  "Estado": "activa",
  "Fecha_inicio": "08\/12\/2023",
  "Fecha_fin": "24\/12\/2023",
  "SKU": 101160954,
  "para_quien": "Secret Santa",
  "edad": "Adulto",
  "img": "https:\/\/siman.vtexassets.com\/arquivos\/ids\/388380-1600-auto?v=637253677913830000&width=1600&height=auto&aspect=true",
  "url": "https:\/\/sv.siman.com\/waflera-101160954\/p",
  "Precio_regular": 57.9,
  "Precio_promocion": 44,
  "Pais": "SV",
  "Inventario": 61
 },
 {
  "Estado": "activa",
  "Fecha_inicio": "08\/12\/2023",
  "Fecha_fin": "24\/12\/2023",
  "SKU": 103534563,
  "para_quien": "Secret Santa",
  "edad": "Adulto",
  "img": "https:\/\/siman.vtexassets.com\/arquivos\/ids\/1885547-1600-auto?v=637725921420300000&width=1600&height=auto&aspect=true",
  "url": "https:\/\/sv.siman.com\/cafetera-4-en-1-filtro-5tz-103534563\/p",
  "Precio_regular": 43.9,
  "Precio_promocion": 34,
  "Pais": "SV",
  "Inventario": 376
 },
 {
  "Estado": "activa",
  "Fecha_inicio": "08\/12\/2023",
  "Fecha_fin": "24\/12\/2023",
  "SKU": 103450017,
  "para_quien": "Secret Santa",
  "edad": "Adulto",
  "img": "https:\/\/siman.vtexassets.com\/arquivos\/ids\/2724888-1600-auto?v=637834927337730000&width=1600&height=auto&aspect=true",
  "url": "https:\/\/sv.siman.com\/cafetera-5-tazas-black-650w-103450017\/p",
  "Precio_regular": 31.9,
  "Precio_promocion": 25,
  "Pais": "SV",
  "Inventario": 408
 },
 {
  "Estado": "activa",
  "Fecha_inicio": "08\/12\/2023",
  "Fecha_fin": "24\/12\/2023",
  "SKU": 101526924,
  "para_quien": "Secret Santa",
  "edad": "Adulto",
  "img": "https:\/\/siman.vtexassets.com\/arquivos\/ids\/332679-1600-auto?v=637250666587370000&width=1600&height=auto&aspect=true",
  "url": "https:\/\/sv.siman.com\/tostador-compacto-hamilton-beach-101526924\/p",
  "Precio_regular": 49.9,
  "Precio_promocion": 39.99,
  "Pais": "SV",
  "Inventario": 35
 },
 {
  "Estado": "activa",
  "Fecha_inicio": "08\/12\/2023",
  "Fecha_fin": "24\/12\/2023",
  "SKU": 102949002,
  "para_quien": "Secret Santa",
  "edad": "Adulto",
  "img": "https:\/\/siman.vtexassets.com\/arquivos\/ids\/1492240-1600-auto?v=637596459268900000&width=1600&height=auto&aspect=true",
  "url": "https:\/\/sv.siman.com\/freidora-de-aire-3-5-litros-capacidad-200-c-3-5-litros-reloj-automatico-30-minutos-102949002\/p",
  "Precio_regular": 109.9,
  "Precio_promocion": 89.99,
  "Pais": "SV",
  "Inventario": 250
 },
 {
  "Estado": "activa",
  "Fecha_inicio": "08\/12\/2023",
  "Fecha_fin": "24\/12\/2023",
  "SKU": 104011830,
  "para_quien": "Secret Santa",
  "edad": "Adulto",
  "img": "https:\/\/siman.vtexassets.com\/arquivos\/ids\/3790636-1600-auto?v=638071747305630000&width=1600&height=auto&aspect=true",
  "url": "https:\/\/sv.siman.com\/tostadora-4-rebanadas-acero-inoxidable-104011830\/p",
  "Precio_regular": 69.9,
  "Precio_promocion": 59.99,
  "Pais": "SV",
  "Inventario": 23
 },
 {
  "Estado": "activa",
  "Fecha_inicio": "08\/12\/2023",
  "Fecha_fin": "24\/12\/2023",
  "SKU": 436274000000,
  "para_quien": "Secret Santa",
  "edad": "Adulto",
  "img": "https:\/\/siman.vtexassets.com\/arquivos\/ids\/1492562-1600-auto?v=637596460048070000&width=1600&height=auto&aspect=true ",
  "url": "https:\/\/sv.siman.com\/parilla-tipo-plancha-362740\/p ",
  "Precio_regular": 63.9,
  "Precio_promocion": 54.99,
  "Pais": "SV",
  "Inventario": 386
 },
 {
  "Estado": "activa",
  "Fecha_inicio": "08\/12\/2023",
  "Fecha_fin": "24\/12\/2023",
  "SKU": 100559427,
  "para_quien": "Secret Santa",
  "edad": "Adulto",
  "img": "https:\/\/siman.vtexassets.com\/arquivos\/ids\/320428-1600-auto?v=637250570931900000&width=1600&height=auto&aspect=true ",
  "url": "https:\/\/sv.siman.com\/waflera-hamilton-beach-de-2-unidades-100559427\/p ",
  "Precio_regular": 49.9,
  "Precio_promocion": 42.99,
  "Pais": "SV",
  "Inventario": 28
 },
 {
  "Estado": "activa",
  "Fecha_inicio": "08\/12\/2023",
  "Fecha_fin": "24\/12\/2023",
  "SKU": 497513400005,
  "para_quien": "Secret Santa",
  "edad": "Adulto",
  "img": "https:\/\/siman.vtexassets.com\/arquivos\/ids\/1492730-1600-auto?v=637596460456100000&width=1600&height=auto&aspect=true",
  "url": "https:\/\/sv.siman.com\/cafetera-personal-vaso-plastico-16oz-975134\/p",
  "Precio_regular": 25.9,
  "Precio_promocion": 22.99,
  "Pais": "SV",
  "Inventario": 1231
 },
 {
  "Estado": "activa",
  "Fecha_inicio": "08\/12\/2023",
  "Fecha_fin": "24\/12\/2023",
  "SKU": 104208245,
  "para_quien": "Secret Santa",
  "edad": "Adulto",
  "img": "https:\/\/siman.vtexassets.com\/arquivos\/ids\/4410685-1600-auto?v=638237402561200000&width=1600&height=auto&aspect=true",
  "url": "https:\/\/sv.siman.com\/cafetera-7-en-1-compacta-negra-104208245\/p",
  "Precio_regular": 89.9,
  "Precio_promocion": 79.99,
  "Pais": "SV",
  "Inventario": 23
 },
 {
  "Estado": "activa",
  "Fecha_inicio": "08\/12\/2023",
  "Fecha_fin": "24\/12\/2023",
  "SKU": 104228651,
  "para_quien": "Secret Santa",
  "edad": "Adulto",
  "img": "https:\/\/siman.vtexassets.com\/arquivos\/ids\/4442550-1600-auto?v=638247947135500000&width=1600&height=auto&aspect=true",
  "url": "https:\/\/sv.siman.com\/cafetera-12-tazas-negra-programable-1000w-104228651\/p",
  "Precio_regular": 69.9,
  "Precio_promocion": 62.99,
  "Pais": "SV",
  "Inventario": 125
 },
 {
  "Estado": "activa",
  "Fecha_inicio": "08\/12\/2023",
  "Fecha_fin": "24\/12\/2023",
  "SKU": 101374002,
  "para_quien": "Secret Santa",
  "edad": "Adulto",
  "img": "https:\/\/siman.vtexassets.com\/arquivos\/ids\/1491715-1600-auto?v=637596457952030000&width=1600&height=auto&aspect=true",
  "url": "https:\/\/sv.siman.com\/horno-con-conveccion-natural-101374002\/p",
  "Precio_regular": 49.9,
  "Precio_promocion": 44.99,
  "Pais": "SV",
  "Inventario": 313
 },
 {
  "Estado": "activa",
  "Fecha_inicio": "08\/12\/2023",
  "Fecha_fin": "24\/12\/2023",
  "SKU": 103605791,
  "para_quien": "Secret Santa",
  "edad": "Adulto",
  "img": "https:\/\/siman.vtexassets.com\/arquivos\/ids\/2607933-1600-auto?v=637800359376530000&width=1600&height=auto&aspect=true",
  "url": "https:\/\/sv.siman.com\/mini-sandwichera-103605791\/p",
  "Precio_regular": 29.9,
  "Precio_promocion": 29.9,
  "Pais": "SV",
  "Inventario": 96
 },
 {
  "Estado": "activa",
  "Fecha_inicio": "08\/12\/2023",
  "Fecha_fin": "24\/12\/2023",
  "SKU": 104300138,
  "para_quien": "Secret Santa",
  "edad": "Adulto",
  "img": "https:\/\/siman.vtexassets.com\/arquivos\/ids\/4596785-1600-auto?v=638284228680000000&width=1600&height=auto&aspect=true",
  "url": "https:\/\/sv.siman.com\/maquina-para-hacer-conos-y-waffle-pequea-104300138\/p",
  "Precio_regular": 39.9,
  "Precio_promocion": 39.9,
  "Pais": "SV",
  "Inventario": 91
 },
 {
  "Estado": "activa",
  "Fecha_inicio": "08\/12\/2023",
  "Fecha_fin": "24\/12\/2023",
  "SKU": 103605790,
  "para_quien": "Secret Santa",
  "edad": "Adulto",
  "img": "https:\/\/siman.vtexassets.com\/arquivos\/ids\/2607928-1600-auto?v=637800359364800000&width=1600&height=auto&aspect=true",
  "url": "https:\/\/sv.siman.com\/mini-parrilla-electrica-103605790\/p",
  "Precio_regular": 29.9,
  "Precio_promocion": 29.9,
  "Pais": "SV",
  "Inventario": 91
 },
 {
  "Estado": "activa",
  "Fecha_inicio": "08\/12\/2023",
  "Fecha_fin": "24\/12\/2023",
  "SKU": 104365672,
  "para_quien": "Secret Santa",
  "edad": "Adulto",
  "img": "https:\/\/siman.vtexassets.com\/arquivos\/ids\/4738362-1600-auto?v=638315074042630000&width=1600&height=auto&aspect=true",
  "url": "https:\/\/sv.siman.com\/cafetera-ndg-piccolo-negra-127v-104365672\/p",
  "Precio_regular": 109.9,
  "Precio_promocion": 109.9,
  "Pais": "SV",
  "Inventario": 71
 },
 {
  "Estado": "activa",
  "Fecha_inicio": "08\/12\/2023",
  "Fecha_fin": "24\/12\/2023",
  "SKU": 104299921,
  "para_quien": "Secret Santa",
  "edad": "Adulto",
  "img": "https:\/\/siman.vtexassets.com\/arquivos\/ids\/4596779-1600-auto?v=638284228660200000&width=1600&height=auto&aspect=true",
  "url": "https:\/\/sv.siman.com\/maquina-para-hacer-waffle-pequea-doble-104299921\/p",
  "Precio_regular": 29.9,
  "Precio_promocion": 29.9,
  "Pais": "SV",
  "Inventario": 47
 },
 {
  "Estado": "activa",
  "Fecha_inicio": "08\/12\/2023",
  "Fecha_fin": "24\/12\/2023",
  "SKU": 101423710,
  "para_quien": "Secret Santa",
  "edad": "Adulto",
  "img": "https:\/\/siman.vtexassets.com\/arquivos\/ids\/333642-1600-auto?v=637250674242570000&width=1600&height=auto&aspect=true",
  "url": "https:\/\/sv.siman.com\/tostador-proctor-silex2-rebanadas-101423710\/p",
  "Precio_regular": 29.9,
  "Precio_promocion": 29.9,
  "Pais": "SV",
  "Inventario": 37
 },
 {
  "Estado": "activa",
  "Fecha_inicio": "08\/12\/2023",
  "Fecha_fin": "24\/12\/2023",
  "SKU": 100222734,
  "para_quien": "Secret Santa",
  "edad": "Adulto",
  "img": "https:\/\/siman.vtexassets.com\/arquivos\/ids\/318130-1600-auto?v=637250554103770000&width=1600&height=auto&aspect=true",
  "url": "https:\/\/sv.siman.com\/licuadora-personal-100222734\/p",
  "Precio_regular": 29.9,
  "Precio_promocion": 29.9,
  "Pais": "SV",
  "Inventario": 359
 },
 {
  "Estado": "activa",
  "Fecha_inicio": "08\/12\/2023",
  "Fecha_fin": "24\/12\/2023",
  "SKU": 102290232,
  "para_quien": "Secret Santa",
  "edad": "Adulto",
  "img": "https:\/\/siman.vtexassets.com\/arquivos\/ids\/359996-1600-auto?v=637250896670030000&width=1600&height=auto&aspect=true",
  "url": "https:\/\/sv.siman.com\/licuadora-personal-102290232\/p",
  "Precio_regular": 29.9,
  "Precio_promocion": 29.9,
  "Pais": "SV",
  "Inventario": 327
 },
 {
  "Estado": "activa",
  "Fecha_inicio": "08\/12\/2023",
  "Fecha_fin": "24\/12\/2023",
  "SKU": 100222767,
  "para_quien": "Secret Santa",
  "edad": "Adulto",
  "img": "https:\/\/siman.vtexassets.com\/arquivos\/ids\/318132-1600-auto?v=637250554111900000&width=1600&height=auto&aspect=true",
  "url": "https:\/\/sv.siman.com\/licuadora-personal-100222767\/p",
  "Precio_regular": 29.9,
  "Precio_promocion": 29.9,
  "Pais": "SV",
  "Inventario": 309
 },
 {
  "Estado": "activa",
  "Fecha_inicio": "08\/12\/2023",
  "Fecha_fin": "24\/12\/2023",
  "SKU": 100258108,
  "para_quien": "Secret Santa",
  "edad": "Adulto",
  "img": "https:\/\/siman.vtexassets.com\/arquivos\/ids\/318303-1600-auto?v=637250555169530000&width=1600&height=auto&aspect=true",
  "url": "https:\/\/sv.siman.com\/licuadora-personal-100258108\/p",
  "Precio_regular": 29.9,
  "Precio_promocion": 29.9,
  "Pais": "SV",
  "Inventario": 285
 },
 {
  "Estado": "activa",
  "Fecha_inicio": "08\/12\/2023",
  "Fecha_fin": "24\/12\/2023",
  "SKU": 100222860,
  "para_quien": "Secret Santa",
  "edad": "Adulto",
  "img": "https:\/\/siman.vtexassets.com\/arquivos\/ids\/318134-1600-auto?v=637250554120830000&width=1600&height=auto&aspect=true",
  "url": "https:\/\/sv.siman.com\/licuadora-personal-100222860\/p",
  "Precio_regular": 29.9,
  "Precio_promocion": 29.9,
  "Pais": "SV",
  "Inventario": 185
 },
 {
  "Estado": "activa",
  "Fecha_inicio": "08\/12\/2023",
  "Fecha_fin": "24\/12\/2023",
  "SKU": 103357974,
  "para_quien": "Secret Santa",
  "edad": "Adulto",
  "img": "https:\/\/siman.vtexassets.com\/arquivos\/ids\/1506871-1600-auto?v=637601462218300000&width=1600&height=auto&aspect=true",
  "url": "https:\/\/sv.siman.com\/licuadora-personal-120w-103357974\/p",
  "Precio_regular": 89.9,
  "Precio_promocion": 79.99,
  "Pais": "SV",
  "Inventario": 39
 },
 {
  "Estado": "activa",
  "Fecha_inicio": "08\/12\/2023",
  "Fecha_fin": "24\/12\/2023",
  "SKU": 103019012,
  "para_quien": "Secret Santa",
  "edad": "Adulto",
  "img": "https:\/\/siman.vtexassets.com\/arquivos\/ids\/967036-1600-auto?v=637412257018800000&width=1600&height=auto&aspect=true",
  "url": "https:\/\/sv.siman.com\/megapack-de-ondulador-alisadora-y-secadora-103019012\/p",
  "Precio_regular": 119.9,
  "Precio_promocion": 89,
  "Pais": "SV",
  "Inventario": 295
 },
 {
  "Estado": "activa",
  "Fecha_inicio": "08\/12\/2023",
  "Fecha_fin": "24\/12\/2023",
  "SKU": 104224703,
  "para_quien": "Secret Santa",
  "edad": "Adulto",
  "img": "https:\/\/siman.vtexassets.com\/arquivos\/ids\/4411152-1600-auto?v=638237404179530000&width=1600&height=auto&aspect=true",
  "url": "https:\/\/sv.siman.com\/cortadora-de-cabello-grooming-kit-104224703\/p",
  "Precio_regular": 32,
  "Precio_promocion": 28.99,
  "Pais": "SV",
  "Inventario": 185
 },
 {
  "Estado": "activa",
  "Fecha_inicio": "08\/12\/2023",
  "Fecha_fin": "24\/12\/2023",
  "SKU": 104060105,
  "para_quien": "Secret Santa",
  "edad": "Adulto",
  "img": "https:\/\/siman.vtexassets.com\/arquivos\/ids\/3968858-1600-auto?v=638127607432730000&width=1600&height=auto&aspect=true",
  "url": "https:\/\/sv.siman.com\/plancha-alisadora-coconut-smooth-104060105\/p",
  "Precio_regular": 75.9,
  "Precio_promocion": 67.99,
  "Pais": "SV",
  "Inventario": 179
 },
 {
  "Estado": "activa",
  "Fecha_inicio": "08\/12\/2023",
  "Fecha_fin": "24\/12\/2023",
  "SKU": 103638193,
  "para_quien": "Secret Santa",
  "edad": "Adulto",
  "img": "https:\/\/siman.vtexassets.com\/arquivos\/ids\/2783816-1600-auto?v=637849620954930000&width=1600&height=auto&aspect=true",
  "url": "https:\/\/sv.siman.com\/recortadora-de-cabello-y-afeitadora-103638193\/p",
  "Precio_regular": 49.9,
  "Precio_promocion": 33.99,
  "Pais": "SV",
  "Inventario": 166
 },
 {
  "Estado": "activa",
  "Fecha_inicio": "08\/12\/2023",
  "Fecha_fin": "24\/12\/2023",
  "SKU": 443932500000,
  "para_quien": "Secret Santa",
  "edad": "Adulto",
  "img": "https:\/\/siman.vtexassets.com\/arquivos\/ids\/372268-1600-auto?v=637250982281230000&width=1600&height=auto&aspect=true",
  "url": "https:\/\/sv.siman.com\/rasuradora-dual-flex-cabezales-flexibles-439325\/p",
  "Precio_regular": 38.9,
  "Precio_promocion": 32.99,
  "Pais": "SV",
  "Inventario": 144
 },
 {
  "Estado": "activa",
  "Fecha_inicio": "08\/12\/2023",
  "Fecha_fin": "24\/12\/2023",
  "SKU": 103623230,
  "para_quien": "Secret Santa",
  "edad": "Adulto",
  "img": "https:\/\/siman.vtexassets.com\/arquivos\/ids\/2818162-1600-auto?v=637861519895970000&width=1600&height=auto&aspect=true",
  "url": "https:\/\/sv.siman.com\/combo-w2s-alisadora-y-secador-110-103623230\/p",
  "Precio_regular": 134.9,
  "Precio_promocion": 99,
  "Pais": "SV",
  "Inventario": 135
 },
 {
  "Estado": "activa",
  "Fecha_inicio": "08\/12\/2023",
  "Fecha_fin": "24\/12\/2023",
  "SKU": 103988907,
  "para_quien": "Secret Santa",
  "edad": "Adulto",
  "img": "https:\/\/siman.vtexassets.com\/arquivos\/ids\/3790587-1600-auto?v=638071747198630000&width=1600&height=auto&aspect=true",
  "url": "https:\/\/sv.siman.com\/plancha-ultra-straight-1-roja-revlon-103988907\/p",
  "Precio_regular": 23.9,
  "Precio_promocion": 19.99,
  "Pais": "SV",
  "Inventario": 114
 },
 {
  "Estado": "activa",
  "Fecha_inicio": "08\/12\/2023",
  "Fecha_fin": "24\/12\/2023",
  "SKU": 103638194,
  "para_quien": "Secret Santa",
  "edad": "Adulto",
  "img": "https:\/\/siman.vtexassets.com\/arquivos\/ids\/2783821-1600-auto?v=637849620971200000&width=1600&height=auto&aspect=true",
  "url": "https:\/\/sv.siman.com\/afeitadora-5cutting-levels-103638194\/p",
  "Precio_regular": 29.9,
  "Precio_promocion": 20.99,
  "Pais": "SV",
  "Inventario": 103
 },
 {
  "Estado": "activa",
  "Fecha_inicio": "08\/12\/2023",
  "Fecha_fin": "24\/12\/2023",
  "SKU": 103728479,
  "para_quien": "Secret Santa",
  "edad": "Adulto",
  "img": "https:\/\/siman.vtexassets.com\/arquivos\/ids\/2872842-1600-auto?v=637877212611300000&width=1600&height=auto&aspect=true",
  "url": "https:\/\/sv.siman.com\/cepillo-revlon-onestep-plus-negro-103728479\/p",
  "Precio_regular": 89.9,
  "Precio_promocion": 59.99,
  "Pais": "SV",
  "Inventario": 96
 },
 {
  "Estado": "activa",
  "Fecha_inicio": "08\/12\/2023",
  "Fecha_fin": "24\/12\/2023",
  "SKU": 103728472,
  "para_quien": "Secret Santa",
  "edad": "Adulto",
  "img": "https:\/\/siman.vtexassets.com\/arquivos\/ids\/3094481-1600-auto?v=637927476907970000&width=1600&height=auto&aspect=true",
  "url": "https:\/\/sv.siman.com\/cepillo-secador-air-brush-110v-babyliss-n-t-3-5-103728472\/p",
  "Precio_regular": 89.9,
  "Precio_promocion": 79.99,
  "Pais": "SV",
  "Inventario": 94
 },
 {
  "Estado": "activa",
  "Fecha_inicio": "08\/12\/2023",
  "Fecha_fin": "24\/12\/2023",
  "SKU": 104288635,
  "para_quien": "Secret Santa",
  "edad": "Adulto",
  "img": "https:\/\/siman.vtexassets.com\/arquivos\/ids\/4680463-1600-auto?v=638302332172100000&width=1600&height=auto&aspect=true",
  "url": "https:\/\/sv.siman.com\/rizador-y-secador-one-step-1-negro-rojo-104288635\/p",
  "Precio_regular": 92.9,
  "Precio_promocion": 84.99,
  "Pais": "SV",
  "Inventario": 93
 },
 {
  "Estado": "activa",
  "Fecha_inicio": "08\/12\/2023",
  "Fecha_fin": "24\/12\/2023",
  "SKU": 103988889,
  "para_quien": "Secret Santa",
  "edad": "Adulto",
  "img": "https:\/\/siman.vtexassets.com\/arquivos\/ids\/3790583-1600-auto?v=638071747189600000&width=1600&height=auto&aspect=true",
  "url": "https:\/\/sv.siman.com\/plancha-ultra-straight-1-purp-revlon-103988889\/p",
  "Precio_regular": 23.9,
  "Precio_promocion": 19.99,
  "Pais": "SV",
  "Inventario": 85
 },
 {
  "Estado": "activa",
  "Fecha_inicio": "08\/12\/2023",
  "Fecha_fin": "24\/12\/2023",
  "SKU": 104288340,
  "para_quien": "Secret Santa",
  "edad": "Adulto",
  "img": "https:\/\/siman.vtexassets.com\/arquivos\/ids\/4704576-1600-auto?v=638309023289130000&width=1600&height=auto&aspect=true",
  "url": "https:\/\/sv.siman.com\/secadora-versatil-roja-104288340\/p",
  "Precio_regular": 79.9,
  "Precio_promocion": 74.99,
  "Pais": "SV",
  "Inventario": 80
 },
 {
  "Estado": "activa",
  "Fecha_inicio": "08\/12\/2023",
  "Fecha_fin": "24\/12\/2023",
  "SKU": 103637693,
  "para_quien": "Secret Santa",
  "edad": "Adulto",
  "img": "https:\/\/siman.vtexassets.com\/arquivos\/ids\/2783787-1600-auto?v=637849620814470000&width=1600&height=auto&aspect=true",
  "url": "https:\/\/sv.siman.com\/afeitadora-lavable-navaja-de-45-103637693\/p",
  "Precio_regular": 69.9,
  "Precio_promocion": 53.99,
  "Pais": "SV",
  "Inventario": 80
 },
 {
  "Estado": "activa",
  "Fecha_inicio": "08\/12\/2023",
  "Fecha_fin": "24\/12\/2023",
  "SKU": 102833817,
  "para_quien": "Secret Santa",
  "edad": "Adulto",
  "img": "https:\/\/siman.vtexassets.com\/arquivos\/ids\/810422-1600-auto?v=637346665849630000&width=1600&height=auto&aspect=true",
  "url": "https:\/\/sv.siman.com\/masajeador-vidrador-para-cuello-y-hombros-con-calor-102833817\/p",
  "Precio_regular": 44.9,
  "Precio_promocion": 34.99,
  "Pais": "SV",
  "Inventario": 68
 },
 {
  "Estado": "activa",
  "Fecha_inicio": "08\/12\/2023",
  "Fecha_fin": "24\/12\/2023",
  "SKU": 104194913,
  "para_quien": "Secret Santa",
  "edad": "Adulto",
  "img": "https:\/\/siman.vtexassets.com\/arquivos\/ids\/4332500-1600-auto?v=638217724630570000&width=1600&height=auto&aspect=true",
  "url": "https:\/\/sv.siman.com\/afeitadora-wet-dry-diseo-ergonomico-104194913\/p",
  "Precio_regular": 59.9,
  "Precio_promocion": 40.99,
  "Pais": "SV",
  "Inventario": 55
 },
 {
  "Estado": "activa",
  "Fecha_inicio": "08\/12\/2023",
  "Fecha_fin": "24\/12\/2023",
  "SKU": 104097083,
  "para_quien": "Secret Santa",
  "edad": "Adulto",
  "img": "https:\/\/siman.vtexassets.com\/arquivos\/ids\/4978457-1600-auto?v=638364416547800000&width=1600&height=auto&aspect=true",
  "url": "https:\/\/sv.siman.com\/cepillo-electrico-104097083\/p",
  "Precio_regular": 73.9,
  "Precio_promocion": 59,
  "Pais": "SV",
  "Inventario": 54
 },
 {
  "Estado": "activa",
  "Fecha_inicio": "08\/12\/2023",
  "Fecha_fin": "24\/12\/2023",
  "SKU": 104224704,
  "para_quien": "Secret Santa",
  "edad": "Adulto",
  "img": "https:\/\/siman.vtexassets.com\/arquivos\/ids\/4411156-1600-auto?v=638237404191800000&width=1600&height=auto&aspect=true",
  "url": "https:\/\/sv.siman.com\/recortador-de-barba-y-detalles-kit-todo-en-1-104224704\/p",
  "Precio_regular": 65.9,
  "Precio_promocion": 59.99,
  "Pais": "SV",
  "Inventario": 51
 },
 {
  "Estado": "activa",
  "Fecha_inicio": "08\/12\/2023",
  "Fecha_fin": "24\/12\/2023",
  "SKU": 104368671,
  "para_quien": "Secret Santa",
  "edad": "Adulto",
  "img": "https:\/\/siman.vtexassets.com\/arquivos\/ids\/4789426-1600-auto?v=638326565852000000&width=1600&height=auto&aspect=true",
  "url": "https:\/\/sv.siman.com\/mini-detallador-de-cabello-3-en-1-seco-y-mojado-con-baterias-3-cabezales-negro-104368671\/p",
  "Precio_regular": 17.9,
  "Precio_promocion": 17.9,
  "Pais": "SV",
  "Inventario": 50
 },
 {
  "Estado": "activa",
  "Fecha_inicio": "08\/12\/2023",
  "Fecha_fin": "24\/12\/2023",
  "SKU": 104352023,
  "para_quien": "Secret Santa",
  "edad": "Adulto",
  "img": "https:\/\/siman.vtexassets.com\/arquivos\/ids\/4839284-1600-auto?v=638336950043470000&width=1600&height=auto&aspect=true",
  "url": "https:\/\/sv.siman.com\/combo-de-secadora-plancha-essential-purpura-104352023\/p",
  "Precio_regular": 54.9,
  "Precio_promocion": 39.99,
  "Pais": "SV",
  "Inventario": 50
 },
 {
  "Estado": "activa",
  "Fecha_inicio": "08\/12\/2023",
  "Fecha_fin": "24\/12\/2023",
  "SKU": 103363462,
  "para_quien": "Secret Santa",
  "edad": "Adulto",
  "img": "https:\/\/siman.vtexassets.com\/arquivos\/ids\/1507060-1600-auto?v=637601462964500000&width=1600&height=auto&aspect=true",
  "url": "https:\/\/sv.siman.com\/afeitadora-para-hombre-103363462\/p",
  "Precio_regular": 139.9,
  "Precio_promocion": 96.99,
  "Pais": "SV",
  "Inventario": 48
 },
 {
  "Estado": "activa",
  "Fecha_inicio": "08\/12\/2023",
  "Fecha_fin": "24\/12\/2023",
  "SKU": 100162212,
  "para_quien": "Secret Santa",
  "edad": "Adulto",
  "img": "https:\/\/siman.vtexassets.com\/arquivos\/ids\/1232586-1600-auto?v=637523636048770000&width=1600&height=auto&aspect=true",
  "url": "https:\/\/sv.siman.com\/afeitadora-deluxe-groom-pro-100162212\/p",
  "Precio_regular": 49.9,
  "Precio_promocion": 49.9,
  "Pais": "SV",
  "Inventario": 46
 },
 {
  "Estado": "activa",
  "Fecha_inicio": "08\/12\/2023",
  "Fecha_fin": "24\/12\/2023",
  "SKU": 102949005,
  "para_quien": "Secret Santa",
  "edad": "Adulto",
  "img": "https:\/\/siman.vtexassets.com\/arquivos\/ids\/1492264-1600-auto?v=637596459331530000&width=1600&height=auto&aspect=true",
  "url": "https:\/\/sv.siman.com\/cortador-de-cabello-con-peines-y-cepillos-para-limpieza-102949005\/p",
  "Precio_regular": 57.9,
  "Precio_promocion": 45.99,
  "Pais": "SV",
  "Inventario": 46
 },
 {
  "Estado": "activa",
  "Fecha_inicio": "08\/12\/2023",
  "Fecha_fin": "24\/12\/2023",
  "SKU": 103348175,
  "para_quien": "Secret Santa",
  "edad": "Adulto",
  "img": "https:\/\/siman.vtexassets.com\/arquivos\/ids\/1465550-1600-auto?v=637587654868430000&width=1600&height=auto&aspect=true",
  "url": "https:\/\/sv.siman.com\/recortador-de-cabello-legacy-103348175\/p",
  "Precio_regular": 80.9,
  "Precio_promocion": 45,
  "Pais": "SV",
  "Inventario": 46
 },
 {
  "Estado": "activa",
  "Fecha_inicio": "08\/12\/2023",
  "Fecha_fin": "24\/12\/2023",
  "SKU": 103050959,
  "para_quien": "Secret Santa",
  "edad": "Adulto",
  "img": "https:\/\/siman.vtexassets.com\/arquivos\/ids\/911860-1600-auto?v=637390867477300000&width=1600&height=auto&aspect=true",
  "url": "https:\/\/sv.siman.com\/secadora-nano-purpura-1800-2000w-103050959\/p",
  "Precio_regular": 99.9,
  "Precio_promocion": 69.99,
  "Pais": "SV",
  "Inventario": 45
 },
 {
  "Estado": "activa",
  "Fecha_inicio": "08\/12\/2023",
  "Fecha_fin": "24\/12\/2023",
  "SKU": 104352024,
  "para_quien": "Secret Santa",
  "edad": "Adulto",
  "img": "https:\/\/siman.vtexassets.com\/arquivos\/ids\/4839287-1600-auto?v=638336950054100000&width=1600&height=auto&aspect=true",
  "url": "https:\/\/sv.siman.com\/combo-de-secadora-plancha-essential-roja-104352024\/p",
  "Precio_regular": 54.9,
  "Precio_promocion": 39.99,
  "Pais": "SV",
  "Inventario": 44
 },
 {
  "Estado": "activa",
  "Fecha_inicio": "08\/12\/2023",
  "Fecha_fin": "24\/12\/2023",
  "SKU": 100036136,
  "para_quien": "Secret Santa",
  "edad": "Adulto",
  "img": "https:\/\/siman.vtexassets.com\/arquivos\/ids\/1491282-1600-auto?v=637596456907130000&width=1600&height=auto&aspect=true",
  "url": "https:\/\/sv.siman.com\/cortadora-remington-100036136\/p",
  "Precio_regular": 59.9,
  "Precio_promocion": 45,
  "Pais": "SV",
  "Inventario": 43
 },
 {
  "Estado": "activa",
  "Fecha_inicio": "08\/12\/2023",
  "Fecha_fin": "24\/12\/2023",
  "SKU": 103858734,
  "para_quien": "Secret Santa",
  "edad": "Adulto",
  "img": "https:\/\/siman.vtexassets.com\/arquivos\/ids\/3301030-1600-auto?v=637976597799900000&width=1600&height=auto&aspect=true",
  "url": "https:\/\/sv.siman.com\/plancha-alisadora-doble-placa-1-2-hasta-445-f-103858734\/p",
  "Precio_regular": 79.9,
  "Precio_promocion": 54.99,
  "Pais": "SV",
  "Inventario": 40
 },
 {
  "Estado": "activa",
  "Fecha_inicio": "08\/12\/2023",
  "Fecha_fin": "24\/12\/2023",
  "SKU": 103993791,
  "para_quien": "Secret Santa",
  "edad": "Adulto",
  "img": "https:\/\/siman.vtexassets.com\/arquivos\/ids\/3684687-1600-auto?v=638047479768270000&width=1600&height=auto&aspect=true",
  "url": "https:\/\/sv.siman.com\/alisadora-kashmira-profesional-ceramica-pro-turquesa-1-control-de-temperatura-103993791\/p",
  "Precio_regular": 99.9,
  "Precio_promocion": 59.99,
  "Pais": "SV",
  "Inventario": 39
 },
 {
  "Estado": "activa",
  "Fecha_inicio": "08\/12\/2023",
  "Fecha_fin": "24\/12\/2023",
  "SKU": 101643674,
  "para_quien": "Secret Santa",
  "edad": "Adulto",
  "img": "https:\/\/siman.vtexassets.com\/arquivos\/ids\/340831-1600-auto?v=637250729324230000&width=1600&height=auto&aspect=true",
  "url": "https:\/\/sv.siman.com\/combo-remington-plancha-y-secadora-triple-infusion-101643674\/p",
  "Precio_regular": 129.9,
  "Precio_promocion": 99.99,
  "Pais": "SV",
  "Inventario": 37
 },
 {
  "Estado": "activa",
  "Fecha_inicio": "08\/12\/2023",
  "Fecha_fin": "24\/12\/2023",
  "SKU": 103298314,
  "para_quien": "Secret Santa",
  "edad": "Adulto",
  "img": "https:\/\/siman.vtexassets.com\/arquivos\/ids\/1327454-1600-auto?v=637553088120000000&width=1600&height=auto&aspect=true",
  "url": "https:\/\/sv.siman.com\/cortadora-se-gbs-absolute-zero-110v-103298314\/p",
  "Precio_regular": 99.9,
  "Precio_promocion": 59.99,
  "Pais": "SV",
  "Inventario": 32
 },
 {
  "Estado": "activa",
  "Fecha_inicio": "08\/12\/2023",
  "Fecha_fin": "24\/12\/2023",
  "SKU": 103324871,
  "para_quien": "Secret Santa",
  "edad": "Adulto",
  "img": "https:\/\/siman.vtexassets.com\/arquivos\/ids\/1408525-1600-auto?v=637571237606400000&width=1600&height=auto&aspect=true",
  "url": "https:\/\/sv.siman.com\/cortadora-de-cabello-y-recortadora-de-barba-103324871\/p",
  "Precio_regular": 34.9,
  "Precio_promocion": 34.9,
  "Pais": "SV",
  "Inventario": 32
 },
 {
  "Estado": "activa",
  "Fecha_inicio": "08\/12\/2023",
  "Fecha_fin": "24\/12\/2023",
  "SKU": 103293832,
  "para_quien": "Secret Santa",
  "edad": "Adulto",
  "img": "https:\/\/siman.vtexassets.com\/arquivos\/ids\/1391797-1600-auto?v=637568612376130000&width=1600&height=auto&aspect=true",
  "url": "https:\/\/sv.siman.com\/cepillo-onestep-volume-styler-rosa-103293832\/p",
  "Precio_regular": 79.9,
  "Precio_promocion": 59.99,
  "Pais": "SV",
  "Inventario": 30
 }
]